Labs/Processor/Lab05/part03/submitted/adder.v
/*
Author - W M D U Thilakarathna
Reg No - E/16/366
*/

module adder(INPUT1, INPUT2, RESULT); // adder module

    input [31:0] INPUT1, INPUT2; // declare inputs
    output reg [31:0] RESULT;    // declare outputs

    always @(*) 
    begin
      #2 RESULT = INPUT1 + INPUT2; // add two numbers 
    end

endmodule

Labs/Processor/Lab05/part01/alu.v
module alu(DATA1, DATA2, RESULT, SELECT);
input [7:0] DATA1, DATA2; //declare the inputs
input [2:0] SELECT; //declare the select input
output [7:0] RESULT; //declare the output

reg [7:0] RESULT; // declare the outputs as registers

always @ (DATA1 or DATA2 or SELECT) // this block run if there is any change in DATA1 or DATA2 or SELECT
begin
    case (SELECT)
    'b000:
        RESULT = #1 DATA2; //forward operation  
    'b001:
        RESULT = #2 DATA1 + DATA2; // add operation
    'b010:
        RESULT = #1 DATA1 & DATA2; // bitwise and operation
    'b011:
        RESULT = #1 DATA1 | DATA2; // bitwise or operation
    default: RESULT = 0; //result 0 if the other cases
    endcase
end
    
endmodule

Labs/Processor/Lab06/part02/mux2to1_32bit.v
/*
Author - W M D U Thilakarathna
Reg No - E/16/366
*/

`timescale 1ns/100ps

module mux2to1_32bit(INPUT1, INPUT2, RESULT, SELECT);
    input [31:0] INPUT1, INPUT2; //declare inputs of the module
    input SELECT;               //declare inputs
    output reg [31:0] RESULT;    //declare outputs

    always @(*)
    begin
      if (SELECT == 1'b0)  //selecting according to the select signal
            RESULT = INPUT1;
      else 
            RESULT = INPUT2;
    end

endmodule

Labs/Processor/Lab06/part03/barrel_shifter/mux2to1_8bit.v
/*
Author - W M D U Thilakarathna
Reg No - E/16/366
*/

module mux2to1_8bit(INPUT1, INPUT2, RESULT, SELECT);
    input [7:0] INPUT1, INPUT2; //declare inputs of the module
    input SELECT;               //declare inputs
    output reg [7:0] RESULT;    //declare outputs

    always @(*)
    begin
      if (SELECT == 1'b0)  //selecting according to the select signal
            RESULT = INPUT1;
      else 
            RESULT = INPUT2;
    end

endmodule

Labs/Processor/Lab05/part03/twosComp.v
module twosComp(INPUT, RESULT); //change this
    input [7:0] INPUT;       //declare inputs
    output reg [7:0] RESULT; //declare outputs

    always @ (INPUT)
    begin
      RESULT = ~INPUT + 1; // 2s comp negative
    end

endmodule

Labs/Processor/Lab05/part02/reg_file.v
module reg_file(IN, OUT1, OUT2, INADDRESS, OUT1ADDRESS, OUT2ADDRESS, WRITE, CLK, RESET);

input [7:0] IN;  // 8 bit data input
input [2:0] INADDRESS, OUT1ADDRESS, OUT2ADDRESS; // 3 bit data inputs
input WRITE, CLK, RESET; // 1 bit data inputs
output [7:0] OUT1, OUT2; // 8 bit data outputs

reg [7:0] OUT1, OUT2; // registers for the output

reg [7:0] registers [7:0]; // 8x8 register file

reg [7:0] OUT1CURR, OUT2CURR; //take the current value of the output to give after delay

integer i;

always @ (posedge CLK) // this code block run when we are in a positive clock edge
begin
    // write input to the in address
    if (WRITE == 1)
        #2 registers[INADDRESS] = IN;     
end


//always run if out1 address or out2 address or their data changed
always @ (OUT1ADDRESS or OUT2ADDRESS or registers[OUT1ADDRESS] or registers[OUT2ADDRESS])
begin
    if (RESET == 0)
    begin
        #2
        OUT1 = registers[OUT1ADDRESS]; //writing data to outputs
        OUT2 = registers[OUT2ADDRESS];  
    end
       
end

// combinational logic output for reset signal (level triggered input)
always @ (*)
begin
    if (RESET == 1)
    begin
        #2 
        for (i = 0; i < 8; i++) //looping through register file and setting them to 0s
        begin
            registers[i] = 0;
        end   

        // after reseting writing for the outputs
        #2    
        OUT1 = registers[OUT1ADDRESS]; 
        OUT2 = registers[OUT2ADDRESS]; 
    end
    
end

endmodule

Labs/Processor/Lab05/part04/control_unit.v
/*
Author - W M D U Thilakarathna
Reg No - E/16/366
*/

module control_unit(OP, twoscompMUXSEL, immeMUXSEL, regWRITEEN, aluOP, jump, RESET);

    parameter [7:0] ADD   = 8'h00, 
                    SUB   = 8'h01,
                    AND   = 8'h02,
                    OR    = 8'h03,
                    MOV   = 8'h04,
                    LOADI = 8'h05,
                    J     = 8'h06,
                    BEQ   = 8'h07;

    input [7:0] OP; //input op code
    input RESET; // RESET input 
    output reg twoscompMUXSEL, immeMUXSEL, regWRITEEN, jump; //output registers
    output reg [2:0] aluOP;

    always @ (*)
    begin
      case (OP)
        ADD:
            begin
                #1
                twoscompMUXSEL = 1'b0; //twos compliment select mux
                immeMUXSEL = 1'b0;     //immediate value select mux
                regWRITEEN = 1'b1;     //regwrite enable pin
                aluOP = 3'b001;        //cpu op code  
                jump = 1'b0;           //jump instruction
            end

        SUB:
            begin
                #1
                twoscompMUXSEL = 1'b1; //twos compliment select mux
                immeMUXSEL = 1'b0;     //immediate value select mux
                regWRITEEN = 1'b1;     //regwrite enable pin
                aluOP = 3'b001;        //cpu op code  
                jump = 1'b0;           //jump instruction
            end

        AND:
            begin
                #1
                twoscompMUXSEL = 1'b0; //twos compliment select mux
                immeMUXSEL = 1'b0;     //immediate value select mux
                regWRITEEN = 1'b1;     //regwrite enable pin
                aluOP = 3'b010;        //cpu op code  
                jump = 1'b0;           //jump instruction
            end

        OR:
            begin
                #1
                twoscompMUXSEL = 1'b0; //twos compliment select mux
                immeMUXSEL = 1'b0;     //immediate value select mux
                regWRITEEN = 1'b1;     //regwrite enable pin
                aluOP = 3'b011;        //cpu op code  
                jump = 1'b0;           //jump instruction
            end

        MOV:
            begin
                #1
                twoscompMUXSEL = 1'b0; //twos compliment select mux
                immeMUXSEL = 1'b0;     //immediate value select mux
                regWRITEEN = 1'b1;     //regwrite enable pin
                aluOP = 3'b000;        //cpu op code  
                jump = 1'b0;           //jump instruction
            end

        LOADI:
            begin
                #1
                twoscompMUXSEL = 1'b0; //twos compliment select mux
                immeMUXSEL = 1'b1;     //immediate value select mux
                regWRITEEN = 1'b1;     //regwrite enable pin
                aluOP = 3'b000;        //cpu op code  
                jump = 1'b0;           //jump instruction
            end

        J:
            begin
                #1
                twoscompMUXSEL = 1'b1; //twos compliment select mux
                immeMUXSEL = 1'b0;     //immediate value select mux
                regWRITEEN = 1'b0;     //regwrite enable pin
                aluOP = 3'b001;        //cpu op code  
                jump = 1'b1;           //jump instruction
            end
        endcase
    end

    always @ (*) //if reset set the pc select
    begin
      if (RESET) jump = 0;
    end

endmodule

Labs/Processor/Lab05/part04/cpu.v
/*
Author - W M D U Thilakarathna
Reg No - E/16/366
*/

`include "alu.v"
`include "reg_file.v"
`include "control_unit.v"
`include "twosComp.v"
`include "mux2to1_8bit.v"
`include "mux2to1_32bit.v"
`include "adder.v"

module cpu(PC, INSTRUCTION, CLK, RESET);

    input [31:0] INSTRUCTION; //fetched INSTRUCTIONtructions
    input CLK, RESET; // clock and reset for the cpu
    output reg [31:0] PC; //programme counter

    wire [7:0] SOURCE1, SOURCE2, DESTINATION, OP;  //decoded INSTRUCTIONtructons
    wire twoscompMUXSEL, immeMUXSEL, regWRITEEN, jump;   //control signals
    wire [2:0] aluOP; // alu op code

    wire [7:0] REGOUT1, REGOUT2; //register file outputs
    wire [7:0] ALOP1, ALOP2, ALUOUT; //alu signal
    wire [7:0] TWOSCOMPOUT; //output of the twos complement
    wire [7:0] TWOSMUXOUT; //output of the twos compliment mux

    wire [31:0] PCNEXT; //store the next value of the pc
    wire [31:0] PCINCBY4; //store the next value of the pc + 4
    wire [31:0] PCJUMP; //store the next value of the pc if the instruction is jump

    //initiating the modules
    control_unit mycu (OP, twoscompMUXSEL, immeMUXSEL, regWRITEEN, aluOP, jump, RESET); //control unit module
    reg_file myreg (ALUOUT, REGOUT1, REGOUT2, DESTINATION[2:0], SOURCE1[2:0], SOURCE2[2:0], regWRITEEN, CLK, RESET); //alu module
    twosComp twos (REGOUT2, TWOSCOMPOUT); // twos complement unit
    mux2to1_8bit muxtwos (REGOUT2, TWOSCOMPOUT, TWOSMUXOUT, twoscompMUXSEL); //mux for two to one in the 2s complement selection
    mux2to1_8bit muximme (TWOSMUXOUT, SOURCE2, ALOP1, immeMUXSEL); //immmediate value load mux
    mux2to1_32bit muxjump (PCINCBY4, PCJUMP, PCNEXT, jump); //jump instruction
    alu myalu (ALOP2, ALOP1, ALUOUT, aluOP); //alu module 
    adder myadder (PC, 32'h00000004, PCINCBY4); //adder to increment the cpu
    adder jumpadder (PCINCBY4, {{22{DESTINATION[7]}}, DESTINATION, 2'b00}, PCJUMP); //adder for the jump instruction

    // decoding the INSTRUCTIONtructions
    assign DESTINATION = INSTRUCTION[23:16];
    assign SOURCE1 = INSTRUCTION[16:8];
    assign SOURCE2 = INSTRUCTION[7:0];
    assign OP = INSTRUCTION[31:24];

    assign ALOP2 = REGOUT1; //connect regout1 with the alu oparand 2

    always @ (posedge CLK)
    begin
      if (RESET == 1'b1) PC = -4; // rest the pc counter
      else #1 PC = PCNEXT;        // increment the pc
    end

    always @ (*)
    begin
      if (RESET == 1'b1) PC = -4; //asynchronus reset for the cpu
    end

endmodule

Labs/Processor/Lab05/part04/testbenchCPU.v
/*
Author - W M D U Thilakarathna
Reg No - E/16/366
*/

`include "cpu.v"

module testbenchCPU;
    
    //input registers
    wire [31:0] INS;
    reg CLK, RESET; 
    reg [7:0] INST_MEMORY [1023:0] ; //instruction array

    wire[31:0] PC;
    
    cpu mycpu(PC, INS, CLK, RESET); //initialize the cpu

    initial // instruction array
    begin
      //monitor command to check the content od the register file
      $monitor($time, " REG0: %b  REG1: %b  REG2: %b  REG3: %b  REG4: %b  REG5: %b  REG6: %b  REG7: %b ",
                          mycpu.myreg.REGISTERS[0], mycpu.myreg.REGISTERS[1], mycpu.myreg.REGISTERS[2], 
                          mycpu.myreg.REGISTERS[3], mycpu.myreg.REGISTERS[4], mycpu.myreg.REGISTERS[5], 
                          mycpu.myreg.REGISTERS[6], mycpu.myreg.REGISTERS[7]);
      // generate files needed to plot the waveform using GTKWave
      $dumpfile("cpu_wavedata.vcd");
      $dumpvars(0, testbenchCPU);
    end

    assign #2 INS = {INST_MEMORY[PC + 3], INST_MEMORY[PC + 2], INST_MEMORY[PC + 1], INST_MEMORY[PC]}; //fetching instruction
       
    initial
    begin
         // loadi 0 0x0A
        {INST_MEMORY[3],INST_MEMORY[2],INST_MEMORY[1],INST_MEMORY[0]}     = 32'b00000101_00000000_00000000_00001010;
        // mov 1 0
        {INST_MEMORY[7],INST_MEMORY[6],INST_MEMORY[5],INST_MEMORY[4]}     = 32'b00000100_00000001_00000000_00000000;
        // loadi 2 0x05
        {INST_MEMORY[11],INST_MEMORY[10],INST_MEMORY[9],INST_MEMORY[8]}   = 32'b00000101_00000010_00000000_00000101;
        // sub 3 1 2
        {INST_MEMORY[15],INST_MEMORY[14],INST_MEMORY[13],INST_MEMORY[12]} = 32'b00000001_00000011_00000001_00000010;
        // or 3 1 2
        {INST_MEMORY[19],INST_MEMORY[18],INST_MEMORY[17],INST_MEMORY[16]} = 32'b00000011_00000011_00000001_00000010;
        // and 3 1 2
        {INST_MEMORY[23],INST_MEMORY[22],INST_MEMORY[21],INST_MEMORY[20]} = 32'b00000010_00000011_00000001_00000010;
        // add 3 1 2
        {INST_MEMORY[27],INST_MEMORY[26],INST_MEMORY[25],INST_MEMORY[24]} = 32'b00000000_00000001_00000001_00000010;
        // j 
        {INST_MEMORY[31],INST_MEMORY[30],INST_MEMORY[29],INST_MEMORY[28]} = 32'b00000110_11111110_00000000_00000000;

        CLK = 1'b1;
        
        // assign values with time to input signals to see output 
        RESET = 1'b1;

        #1
        RESET = 1'b0;

        #37
        RESET = 1'b1;
        #4
        RESET = 1'b0;

        #200
        $finish;
    end
    
    // clock signal generation
    always
    begin
      #7 CLK = ~CLK;       
    end              

endmodule

Labs/Processor/Lab05/part04/cpu_wavedata.vcd
$date
	Thu May 14 12:28:40 2020
$end
$version
	Icarus Verilog
$end
$timescale
	1s
$end
$scope module testbenchCPU $end
$var wire 32 ! PC [31:0] $end
$var wire 32 " INS [31:0] $end
$var reg 1 # CLK $end
$var reg 1 $ RESET $end
$scope module mycpu $end
$var wire 8 % ALOP2 [7:0] $end
$var wire 1 # CLK $end
$var wire 32 & INSTRUCTION [31:0] $end
$var wire 1 $ RESET $end
$var wire 1 ' twoscompMUXSEL $end
$var wire 1 ( regWRITEEN $end
$var wire 1 ) jump $end
$var wire 1 * immeMUXSEL $end
$var wire 3 + aluOP [2:0] $end
$var wire 8 , TWOSMUXOUT [7:0] $end
$var wire 8 - TWOSCOMPOUT [7:0] $end
$var wire 8 . SOURCE2 [7:0] $end
$var wire 8 / SOURCE1 [7:0] $end
$var wire 8 0 REGOUT2 [7:0] $end
$var wire 8 1 REGOUT1 [7:0] $end
$var wire 32 2 PCNEXT [31:0] $end
$var wire 32 3 PCJUMP [31:0] $end
$var wire 32 4 PCINCBY4 [31:0] $end
$var wire 8 5 OP [7:0] $end
$var wire 8 6 DESTINATION [7:0] $end
$var wire 8 7 ALUOUT [7:0] $end
$var wire 8 8 ALOP1 [7:0] $end
$var reg 32 9 PC [31:0] $end
$scope module jumpadder $end
$var wire 32 : INPUT2 [31:0] $end
$var wire 32 ; INPUT1 [31:0] $end
$var reg 32 < RESULT [31:0] $end
$upscope $end
$scope module muximme $end
$var wire 8 = INPUT2 [7:0] $end
$var wire 1 * SELECT $end
$var wire 8 > INPUT1 [7:0] $end
$var reg 8 ? RESULT [7:0] $end
$upscope $end
$scope module muxjump $end
$var wire 32 @ INPUT2 [31:0] $end
$var wire 1 ) SELECT $end
$var wire 32 A INPUT1 [31:0] $end
$var reg 32 B RESULT [31:0] $end
$upscope $end
$scope module muxtwos $end
$var wire 1 ' SELECT $end
$var wire 8 C INPUT2 [7:0] $end
$var wire 8 D INPUT1 [7:0] $end
$var reg 8 E RESULT [7:0] $end
$upscope $end
$scope module myadder $end
$var wire 32 F INPUT1 [31:0] $end
$var wire 32 G INPUT2 [31:0] $end
$var reg 32 H RESULT [31:0] $end
$upscope $end
$scope module myalu $end
$var wire 8 I DATA1 [7:0] $end
$var wire 8 J DATA2 [7:0] $end
$var wire 3 K SELECT [2:0] $end
$var reg 8 L RESULT [7:0] $end
$upscope $end
$scope module mycu $end
$var wire 8 M OP [7:0] $end
$var wire 1 $ RESET $end
$var reg 3 N aluOP [2:0] $end
$var reg 1 * immeMUXSEL $end
$var reg 1 ) jump $end
$var reg 1 ( regWRITEEN $end
$var reg 1 ' twoscompMUXSEL $end
$upscope $end
$scope module myreg $end
$var wire 1 # CLK $end
$var wire 8 O IN [7:0] $end
$var wire 3 P INADDRESS [2:0] $end
$var wire 8 Q OUT1 [7:0] $end
$var wire 3 R OUT1ADDRESS [2:0] $end
$var wire 8 S OUT2 [7:0] $end
$var wire 3 T OUT2ADDRESS [2:0] $end
$var wire 1 $ RESET $end
$var wire 1 ( WRITE $end
$var integer 32 U i [31:0] $end
$upscope $end
$scope module twos $end
$var wire 8 V INPUT [7:0] $end
$var reg 8 W RESULT [7:0] $end
$upscope $end
$upscope $end
$upscope $end
$enddefinitions $end
#0
$dumpvars
bx W
bx V
bx U
bx T
bx S
bx R
bx Q
bx P
bx O
bx N
bx M
bx L
bx K
bx J
bx I
bx H
b100 G
b11111111111111111111111111111100 F
bx E
bx D
bx C
bx B
bx A
bx @
bx ?
bx >
bx =
bx <
bx ;
bx00 :
b11111111111111111111111111111100 9
bx 8
bx 7
bx 6
bx 5
bx 4
bx 3
bx 2
bx 1
bx 0
bx /
bx .
bx -
bx ,
bx +
x*
0)
x(
x'
bx &
bx %
1$
1#
bx "
b11111111111111111111111111111100 !
$end
#1
0$
#2
b0 2
b0 B
b1000 U
b0 4
b0 ;
b0 A
b0 H
#7
0#
#14
1#
#15
b0 !
b0 9
b0 F
#17
b0 R
b0 7
b0 L
b0 O
b0 P
b0 /
b1010 8
b1010 ?
b1010 J
b10 T
b100 2
b100 B
b0 :
b0 6
b1010 .
b1010 =
b101 5
b101 M
b100 4
b100 ;
b100 A
b100 H
b101000000000000000000001010 "
b101000000000000000000001010 &
#18
b0 +
b0 K
b0 N
1(
1*
0'
#19
b0 ,
b0 >
b0 E
b0 -
b0 C
b0 W
b1010 7
b1010 L
b1010 O
b0 %
b0 I
b0 1
b0 Q
b0 0
b0 D
b0 S
b0 V
b100 3
b100 <
b100 @
#21
0#
#28
1#
#29
b100 !
b100 9
b100 F
#31
b1 P
b0 8
b0 ?
b0 J
b0 T
b1000 2
b1000 B
b100 :
b1 6
b0 .
b0 =
b100 5
b100 M
b1000 4
b1000 ;
b1000 A
b1000 H
b100000000010000000000000000 "
b100000000010000000000000000 &
#32
b0 7
b0 L
b0 O
0*
b1010 %
b1010 I
b1010 1
b1010 Q
#33
b1010 8
b1010 ?
b1010 J
b1010 ,
b1010 >
b1010 E
b11110110 -
b11110110 C
b11110110 W
b1010 0
b1010 D
b1010 S
b1010 V
b1100 3
b1100 <
b1100 @
#34
b1010 7
b1010 L
b1010 O
#35
0#
#38
b11111111111111111111111111111100 !
b11111111111111111111111111111100 9
b11111111111111111111111111111100 F
1$
#40
bx R
bx P
bx /
bx T
b0 2
b0 B
bx00 :
bx 6
bx .
bx =
bx 5
bx M
b0 4
b0 ;
b0 A
b0 H
bx "
bx &
b1000 U
#42
bx 8
bx ?
bx J
bx ,
bx >
bx E
bx -
bx C
bx W
bx 3
bx <
bx @
bx %
bx I
bx 1
bx Q
bx 0
bx D
bx S
bx V
0$
1#
#43
bx 7
bx L
bx O
b0 !
b0 9
b0 F
#45
b0 R
b0 P
b0 /
b10 T
b100 2
b100 B
b0 :
b0 6
b1010 .
b1010 =
b101 5
b101 M
b100 4
b100 ;
b100 A
b100 H
b101000000000000000000001010 "
b101000000000000000000001010 &
#46
b1010 8
b1010 ?
b1010 J
1*
#47
b0 ,
b0 >
b0 E
b0 -
b0 C
b0 W
b1010 7
b1010 L
b1010 O
b0 %
b0 I
b0 1
b0 Q
b0 0
b0 D
b0 S
b0 V
b100 3
b100 <
b100 @
#49
0#
#56
1#
#57
b100 !
b100 9
b100 F
#59
b1 P
b0 8
b0 ?
b0 J
b0 T
b1000 2
b1000 B
b100 :
b1 6
b0 .
b0 =
b100 5
b100 M
b1000 4
b1000 ;
b1000 A
b1000 H
b100000000010000000000000000 "
b100000000010000000000000000 &
#60
b0 7
b0 L
b0 O
0*
b1010 %
b1010 I
b1010 1
b1010 Q
#61
b1010 8
b1010 ?
b1010 J
b1010 ,
b1010 >
b1010 E
b11110110 -
b11110110 C
b11110110 W
b1010 0
b1010 D
b1010 S
b1010 V
b1100 3
b1100 <
b1100 @
#62
b1010 7
b1010 L
b1010 O
#63
0#
#70
1#
#71
b1000 !
b1000 9
b1000 F
#73
b10 P
b101 T
b1100 2
b1100 B
b1000 :
b10 6
b101 .
b101 =
b101 5
b101 M
b1100 4
b1100 ;
b1100 A
b1100 H
b101000000100000000000000101 "
b101000000100000000000000101 &
#74
b101 8
b101 ?
b101 J
1*
#75
b0 ,
b0 >
b0 E
b0 -
b0 C
b0 W
b101 7
b101 L
b101 O
b0 0
b0 D
b0 S
b0 V
b10100 3
b10100 <
b10100 @
#77
0#
#84
1#
#85
b1100 !
b1100 9
b1100 F
#87
b1 R
b11 P
b1 /
b10 8
b10 ?
b10 J
b10 T
b10000 2
b10000 B
b1100 :
b11 6
b10 .
b10 =
b1 5
b1 M
b10000 4
b10000 ;
b10000 A
b10000 H
b1000000110000000100000010 "
b1000000110000000100000010 &
#88
b0 8
b0 ?
b0 J
b10 7
b10 L
b10 O
b1 +
b1 K
b1 N
0*
1'
#89
b11111011 8
b11111011 ?
b11111011 J
b11111011 ,
b11111011 >
b11111011 E
b11111011 -
b11111011 C
b11111011 W
b101 0
b101 D
b101 S
b101 V
b11100 3
b11100 <
b11100 @
#90
b101 7
b101 L
b101 O
#91
0#
#98
1#
#99
b10000 !
b10000 9
b10000 F
#101
b10100 2
b10100 B
b11 5
b11 M
b10100 4
b10100 ;
b10100 A
b10100 H
b11000000110000000100000010 "
b11000000110000000100000010 &
#102
b101 8
b101 ?
b101 J
b101 ,
b101 >
b101 E
b11 +
b11 K
b11 N
0'
#103
b1111 7
b1111 L
b1111 O
b100000 3
b100000 <
b100000 @
#105
0#
#112
1#
#113
b10100 !
b10100 9
b10100 F
#115
b11000 2
b11000 B
b10 5
b10 M
b11000 4
b11000 ;
b11000 A
b11000 H
b10000000110000000100000010 "
b10000000110000000100000010 &
#116
b10 +
b10 K
b10 N
#117
b0 7
b0 L
b0 O
b100100 3
b100100 <
b100100 @
#119
0#
#126
1#
#127
b11000 !
b11000 9
b11000 F
#129
b1 P
b11100 2
b11100 B
b100 :
b1 6
b0 5
b0 M
b11100 4
b11100 ;
b11100 A
b11100 H
b10000000100000010 "
b10000000100000010 &
#130
b1 +
b1 K
b1 N
#131
b100000 3
b100000 <
b100000 @
#132
b1111 7
b1111 L
b1111 O
#133
0#
#140
1#
#141
b11100 !
b11100 9
b11100 F
#143
b0 R
b110 P
b0 /
b0 T
b100000 2
b100000 B
b11111111111111111111111111111000 :
b11111110 6
b0 .
b0 =
b110 5
b110 M
b100000 4
b100000 ;
b100000 A
b100000 H
b110111111100000000000000000 "
b110111111100000000000000000 &
#144
b11111011 8
b11111011 ?
b11111011 J
b11111011 ,
b11111011 >
b11111011 E
1)
0(
1'
#145
b11110110 8
b11110110 ?
b11110110 J
b11110110 ,
b11110110 >
b11110110 E
b11110110 -
b11110110 C
b11110110 W
b11000 2
b11000 B
b1010 0
b1010 D
b1010 S
b1010 V
b11000 3
b11000 <
b11000 @
#146
b0 7
b0 L
b0 O
#147
0#
#154
1#
#155
b11000 !
b11000 9
b11000 F
#157
b1 R
b1 P
b1 /
b10 T
b100 :
b1 6
b10 .
b10 =
b0 5
b0 M
b11100 4
b11100 ;
b11100 A
b11100 H
b10000000100000010 "
b10000000100000010 &
#158
b1010 8
b1010 ?
b1010 J
b11100 2
b11100 B
b1010 ,
b1010 >
b1010 E
0)
1(
0'
#159
b101 8
b101 ?
b101 J
b101 ,
b101 >
b101 E
b11111011 -
b11111011 C
b11111011 W
b1111 %
b1111 I
b1111 1
b1111 Q
b101 0
b101 D
b101 S
b101 V
b100000 3
b100000 <
b100000 @
#160
b10100 7
b10100 L
b10100 O
#161
0#
#168
1#
#169
b11100 !
b11100 9
b11100 F
#171
b0 R
b110 P
b0 /
b0 T
b100000 2
b100000 B
b11111111111111111111111111111000 :
b11111110 6
b0 .
b0 =
b110 5
b110 M
b100000 4
b100000 ;
b100000 A
b100000 H
b110111111100000000000000000 "
b110111111100000000000000000 &
#172
b11111011 8
b11111011 ?
b11111011 J
b11111011 ,
b11111011 >
b11111011 E
1)
0(
1'
#173
b11110110 8
b11110110 ?
b11110110 J
b11110110 ,
b11110110 >
b11110110 E
b11110110 -
b11110110 C
b11110110 W
b11000 2
b11000 B
b1010 %
b1010 I
b1010 1
b1010 Q
b1010 0
b1010 D
b1010 S
b1010 V
b11000 3
b11000 <
b11000 @
#174
b0 7
b0 L
b0 O
#175
0#
#182
1#
#183
b11000 !
b11000 9
b11000 F
#185
b1 R
b1 P
b1 /
b10 T
b100 :
b1 6
b10 .
b10 =
b0 5
b0 M
b11100 4
b11100 ;
b11100 A
b11100 H
b10000000100000010 "
b10000000100000010 &
#186
b1010 8
b1010 ?
b1010 J
b11100 2
b11100 B
b1010 ,
b1010 >
b1010 E
0)
1(
0'
#187
b101 8
b101 ?
b101 J
b101 ,
b101 >
b101 E
b11111011 -
b11111011 C
b11111011 W
b10100 %
b10100 I
b10100 1
b10100 Q
b101 0
b101 D
b101 S
b101 V
b100000 3
b100000 <
b100000 @
#188
b11001 7
b11001 L
b11001 O
#189
0#
#196
1#
#197
b11100 !
b11100 9
b11100 F
#199
b0 R
b110 P
b0 /
b0 T
b100000 2
b100000 B
b11111111111111111111111111111000 :
b11111110 6
b0 .
b0 =
b110 5
b110 M
b100000 4
b100000 ;
b100000 A
b100000 H
b110111111100000000000000000 "
b110111111100000000000000000 &
#200
b11111011 8
b11111011 ?
b11111011 J
b11111011 ,
b11111011 >
b11111011 E
1)
0(
1'
#201
b11110110 8
b11110110 ?
b11110110 J
b11110110 ,
b11110110 >
b11110110 E
b11110110 -
b11110110 C
b11110110 W
b11000 2
b11000 B
b1010 %
b1010 I
b1010 1
b1010 Q
b1010 0
b1010 D
b1010 S
b1010 V
b11000 3
b11000 <
b11000 @
#202
b0 7
b0 L
b0 O
#203
0#
#210
1#
#211
b11000 !
b11000 9
b11000 F
#213
b1 R
b1 P
b1 /
b10 T
b100 :
b1 6
b10 .
b10 =
b0 5
b0 M
b11100 4
b11100 ;
b11100 A
b11100 H
b10000000100000010 "
b10000000100000010 &
#214
b1010 8
b1010 ?
b1010 J
b11100 2
b11100 B
b1010 ,
b1010 >
b1010 E
0)
1(
0'
#215
b101 8
b101 ?
b101 J
b101 ,
b101 >
b101 E
b11111011 -
b11111011 C
b11111011 W
b11001 %
b11001 I
b11001 1
b11001 Q
b101 0
b101 D
b101 S
b101 V
b100000 3
b100000 <
b100000 @
#216
b11110 7
b11110 L
b11110 O
#217
0#
#224
1#
#225
b11100 !
b11100 9
b11100 F
#227
b0 R
b110 P
b0 /
b0 T
b100000 2
b100000 B
b11111111111111111111111111111000 :
b11111110 6
b0 .
b0 =
b110 5
b110 M
b100000 4
b100000 ;
b100000 A
b100000 H
b110111111100000000000000000 "
b110111111100000000000000000 &
#228
b11111011 8
b11111011 ?
b11111011 J
b11111011 ,
b11111011 >
b11111011 E
1)
0(
1'
#229
b11110110 8
b11110110 ?
b11110110 J
b11110110 ,
b11110110 >
b11110110 E
b11110110 -
b11110110 C
b11110110 W
b11000 2
b11000 B
b1010 %
b1010 I
b1010 1
b1010 Q
b1010 0
b1010 D
b1010 S
b1010 V
b11000 3
b11000 <
b11000 @
#230
b0 7
b0 L
b0 O
#231
0#
#238
1#
#239
b11000 !
b11000 9
b11000 F
#241
b1 R
b1 P
b1 /
b10 T
b100 :
b1 6
b10 .
b10 =
b0 5
b0 M
b11100 4
b11100 ;
b11100 A
b11100 H
b10000000100000010 "
b10000000100000010 &
#242
b1010 8
b1010 ?
b1010 J
b11100 2
b11100 B
b1010 ,
b1010 >
b1010 E
0)
1(
0'
