Labs/Processor/Lab05/part03/submitted/adder.v
/*
Author - W M D U Thilakarathna
Reg No - E/16/366
*/

module adder(INPUT1, INPUT2, RESULT); // adder module

    input [31:0] INPUT1, INPUT2; // declare inputs
    output reg [31:0] RESULT;    // declare outputs

    always @(*) 
    begin
      #2 RESULT = INPUT1 + INPUT2; // add two numbers 
    end

endmodule

Labs/Processor/Lab05/part04/alu.v
/*
Author - W M D U Thilakarathna
Reg No - E/16/366
*/

module alu(DATA1, DATA2, RESULT, SELECT, COMP);
input [7:0] DATA1, DATA2; //declare the inputs
input [2:0] SELECT; //declare the select input
output [7:0] RESULT; //declare the output
output COMP; //comparator output

reg [7:0] RESULT; // declare the outputs as registers

always @ (DATA1, DATA2, SELECT) // this block run if there is any change in DATA1 or DATA2 or SELECT
begin
    case (SELECT)
    3'b000:
        #1 RESULT = DATA2; //forward operation  1
    3'b001:
        #2 RESULT = DATA1 + DATA2; // add operation 2
    3'b010:
        #1 RESULT = DATA1 & DATA2; // bitwise and operation 1
    3'b011:
        #1 RESULT = DATA1 | DATA2; // bitwise or operation 1
    default: RESULT = 0; //result 0 if the other cases
    endcase
end

assign COMP = ~(RESULT[7]|RESULT[6]|RESULT[5]|RESULT[4]|RESULT[3]|RESULT[2]|RESULT[1]);  //comparator
    
endmodule

Labs/Processor/Lab06/part02/mux2to1_32bit.v
/*
Author - W M D U Thilakarathna
Reg No - E/16/366
*/

`timescale 1ns/100ps

module mux2to1_32bit(INPUT1, INPUT2, RESULT, SELECT);
    input [31:0] INPUT1, INPUT2; //declare inputs of the module
    input SELECT;               //declare inputs
    output reg [31:0] RESULT;    //declare outputs

    always @(*)
    begin
      if (SELECT == 1'b0)  //selecting according to the select signal
            RESULT = INPUT1;
      else 
            RESULT = INPUT2;
    end

endmodule

Labs/Processor/Lab06/part03/barrel_shifter/mux2to1_8bit.v
/*
Author - W M D U Thilakarathna
Reg No - E/16/366
*/

module mux2to1_8bit(INPUT1, INPUT2, RESULT, SELECT);
    input [7:0] INPUT1, INPUT2; //declare inputs of the module
    input SELECT;               //declare inputs
    output reg [7:0] RESULT;    //declare outputs

    always @(*)
    begin
      if (SELECT == 1'b0)  //selecting according to the select signal
            RESULT = INPUT1;
      else 
            RESULT = INPUT2;
    end

endmodule

Labs/Processor/Lab05/part03/twosComp.v
module twosComp(INPUT, RESULT); //change this
    input [7:0] INPUT;       //declare inputs
    output reg [7:0] RESULT; //declare outputs

    always @ (INPUT)
    begin
      RESULT = ~INPUT + 1; // 2s comp negative
    end

endmodule

Labs/Processor/Lab05/part02/reg_file.v
module reg_file(IN, OUT1, OUT2, INADDRESS, OUT1ADDRESS, OUT2ADDRESS, WRITE, CLK, RESET);

input [7:0] IN;  // 8 bit data input
input [2:0] INADDRESS, OUT1ADDRESS, OUT2ADDRESS; // 3 bit data inputs
input WRITE, CLK, RESET; // 1 bit data inputs
output [7:0] OUT1, OUT2; // 8 bit data outputs

reg [7:0] OUT1, OUT2; // registers for the output

reg [7:0] registers [7:0]; // 8x8 register file

reg [7:0] OUT1CURR, OUT2CURR; //take the current value of the output to give after delay

integer i;

always @ (posedge CLK) // this code block run when we are in a positive clock edge
begin
    // write input to the in address
    if (WRITE == 1)
        #2 registers[INADDRESS] = IN;     
end


//always run if out1 address or out2 address or their data changed
always @ (OUT1ADDRESS or OUT2ADDRESS or registers[OUT1ADDRESS] or registers[OUT2ADDRESS])
begin
    if (RESET == 0)
    begin
        #2
        OUT1 = registers[OUT1ADDRESS]; //writing data to outputs
        OUT2 = registers[OUT2ADDRESS];  
    end
       
end

// combinational logic output for reset signal (level triggered input)
always @ (*)
begin
    if (RESET == 1)
    begin
        #2 
        for (i = 0; i < 8; i++) //looping through register file and setting them to 0s
        begin
            registers[i] = 0;
        end   

        // after reseting writing for the outputs
        #2    
        OUT1 = registers[OUT1ADDRESS]; 
        OUT2 = registers[OUT2ADDRESS]; 
    end
    
end

endmodule

Labs/Processor/Lab05/part04/control_unit.v
/*
Author - W M D U Thilakarathna
Reg No - E/16/366
*/

module control_unit(OP, twoscompMUXSEL, immeMUXSEL, regWRITEEN, aluOP, jump, beq, RESET);

    parameter [7:0] ADD   = 8'h00, 
                    SUB   = 8'h01,
                    AND   = 8'h02,
                    OR    = 8'h03,
                    MOV   = 8'h04,
                    LOADI = 8'h05,
                    J     = 8'h06,
                    BEQ   = 8'h07;

    input [7:0] OP; //input op code
    input RESET, ALUCOMP; // RESET input and alu comparator signal
    output reg twoscompMUXSEL, immeMUXSEL, regWRITEEN, jump, beq; //output registers
    output reg [2:0] aluOP;

    always @ (*)
    begin
      case (OP)
        ADD:
            begin
                #1
                twoscompMUXSEL = 1'b0; //twos compliment select mux
                immeMUXSEL = 1'b0;     //immediate value select mux
                regWRITEEN = 1'b1;     //regwrite enable pin
                aluOP = 3'b001;        //cpu op code  
                jump = 1'b0;           //jump instruction
                beq = 1'b0;            //beq instruction
            end

        SUB:
            begin
                #1
                twoscompMUXSEL = 1'b1; //twos compliment select mux
                immeMUXSEL = 1'b0;     //immediate value select mux
                regWRITEEN = 1'b1;     //regwrite enable pin
                aluOP = 3'b001;        //cpu op code  
                jump = 1'b0;           //jump instruction
                beq = 1'b0;            //beq instruction
            end

        AND:
            begin
                #1
                twoscompMUXSEL = 1'b0; //twos compliment select mux
                immeMUXSEL = 1'b0;     //immediate value select mux
                regWRITEEN = 1'b1;     //regwrite enable pin
                aluOP = 3'b010;        //cpu op code  
                jump = 1'b0;           //jump instruction
                beq = 1'b0;            //beq instruction
            end

        OR:
            begin
                #1
                twoscompMUXSEL = 1'b0; //twos compliment select mux
                immeMUXSEL = 1'b0;     //immediate value select mux
                regWRITEEN = 1'b1;     //regwrite enable pin
                aluOP = 3'b011;        //cpu op code  
                jump = 1'b0;           //jump instruction
                beq = 1'b0;            //beq instruction
            end

        MOV:
            begin
                #1
                twoscompMUXSEL = 1'b0; //twos compliment select mux
                immeMUXSEL = 1'b0;     //immediate value select mux
                regWRITEEN = 1'b1;     //regwrite enable pin
                aluOP = 3'b000;        //cpu op code  
                jump = 1'b0;           //jump instruction
                beq = 1'b0;            //beq instruction
            end

        LOADI:
            begin
                #1
                twoscompMUXSEL = 1'b0; //twos compliment select mux
                immeMUXSEL = 1'b1;     //immediate value select mux
                regWRITEEN = 1'b1;     //regwrite enable pin
                aluOP = 3'b000;        //cpu op code  
                jump = 1'b0;           //jump instruction
                beq = 1'b0;            //beq instruction
            end

        J:
            begin
                #1
                twoscompMUXSEL = 1'b1; //twos compliment select mux
                immeMUXSEL = 1'b0;     //immediate value select mux
                regWRITEEN = 1'b0;     //regwrite enable pin
                aluOP = 3'b001;        //cpu op code  
                jump = 1'b1;           //jump instruction
                beq = 1'b0;            //beq instruction
            end

        BEQ:
            begin
                #1
                twoscompMUXSEL = 1'b1; //twos compliment select mux
                immeMUXSEL = 1'b0;     //immediate value select mux
                regWRITEEN = 1'b0;     //regwrite enable pin
                aluOP = 3'b001;        //cpu op code  
                jump = 1'b0;           //jump instruction
                beq = 1'b1;            //beq instruction
            end
        endcase
    end

    always @ (*) //if reset set the pc select
    begin
      if (RESET) 
      begin
        jump = 1'b0;
        beq = 1'b0;
      end
    end

endmodule

Labs/Processor/Lab05/part04/Submitted/cpu.v
/*
Author - W M D U Thilakarathna
Reg No - E/16/366
*/

`include "alu.v"
`include "reg_file.v"
`include "control_unit.v"
`include "twosComp.v"
`include "mux2to1_8bit.v"
`include "mux2to1_32bit.v"
`include "adder.v"

module cpu(PC, INSTRUCTION, CLK, RESET);

    input [31:0] INSTRUCTION; //fetched INSTRUCTIONtructions
    input CLK, RESET; // clock and reset for the cpu
    output reg [31:0] PC; //programme counter

    wire [7:0] SOURCE1, SOURCE2, DESTINATION, OP;  //decoded INSTRUCTIONtructons
    wire twoscompMUXSEL, immeMUXSEL, regWRITEEN, jump, beq, jumpMUXSEL;   //control signals
    wire [2:0] aluOP; // alu op code

    wire [7:0] REGOUT1, REGOUT2; //register file outputs
    wire [7:0] ALOP1, ALOP2, ALUOUT; //alu signal
    wire ALUCOMP; //comparator of the alu
    wire [7:0] TWOSCOMPOUT; //output of the twos complement
    wire [7:0] TWOSMUXOUT; //output of the twos compliment mux

    wire [31:0] PCNEXT; //store the next value of the pc
    wire [31:0] PCINCBY4; //store the next value of the pc + 4
    wire [31:0] PCJUMP; //store the next value of the pc if the instruction is jump

    //initiating the modules
    control_unit mycu (OP, twoscompMUXSEL, immeMUXSEL, regWRITEEN, aluOP, jump, beq, RESET); //control unit module
    reg_file myreg (ALUOUT, REGOUT1, REGOUT2, DESTINATION[2:0], SOURCE1[2:0], SOURCE2[2:0], regWRITEEN, CLK, RESET); //alu module
    twosComp twos (REGOUT2, TWOSCOMPOUT); // twos complement unit
    mux2to1_8bit muxtwos (REGOUT2, TWOSCOMPOUT, TWOSMUXOUT, twoscompMUXSEL); //mux for two to one in the 2s complement selection
    mux2to1_8bit muximme (TWOSMUXOUT, SOURCE2, ALOP1, immeMUXSEL); //immmediate value load mux
    mux2to1_32bit muxjump (PCINCBY4, PCJUMP, PCNEXT, jumpMUXSEL); //jump mux
    alu myalu (ALOP2, ALOP1, ALUOUT, aluOP, ALUCOMP); //alu module 
    adder myadder (PC, 32'h00000004, PCINCBY4); //adder to increment the cpu
    adder jumpadder (PCINCBY4, {{22{DESTINATION[7]}}, DESTINATION, 2'b00}, PCJUMP); //adder for the jump instruction

    //beq and j instructions
    wire ANDOUTBEQ; //out wire for the and gate
    and a1(ANDOUTBEQ, beq, ALUCOMP);  //and gate to decide a successfull beq command
    or o1(jumpMUXSEL, ANDOUTBEQ, jump); //or gate to select the mux for branch

    // decoding the INSTRUCTIONtructions
    assign DESTINATION = INSTRUCTION[23:16];
    assign SOURCE1 = INSTRUCTION[16:8];
    assign SOURCE2 = INSTRUCTION[7:0];
    assign OP = INSTRUCTION[31:24];

    assign ALOP2 = REGOUT1; //connect regout1 with the alu oparand 2

    always @ (posedge CLK)
    begin
      if (RESET == 1'b1) PC = -4; // rest the pc counter
      else #1 PC = PCNEXT;        // increment the pc
    end

    always @ (*)
    begin
      if (RESET == 1'b1) PC = -4; //asynchronus reset for the cpu
    end

endmodule

Labs/Processor/Lab05/part04/testbenchCPU.v
/*
Author - W M D U Thilakarathna
Reg No - E/16/366
*/

`include "cpu.v"

module testbenchCPU;
    
    //input registers
    wire [31:0] INS;
    reg CLK, RESET; 
    reg [7:0] INST_MEMORY [1023:0] ; //instruction array

    wire[31:0] PC;
    
    cpu mycpu(PC, INS, CLK, RESET); //initialize the cpu

    initial // instruction array
    begin
      //monitor command to check the content od the register file
      $monitor($time, " REG0: %b  REG1: %b  REG2: %b  REG3: %b  REG4: %b  REG5: %b  REG6: %b  REG7: %b ",
                          mycpu.myreg.REGISTERS[0], mycpu.myreg.REGISTERS[1], mycpu.myreg.REGISTERS[2], 
                          mycpu.myreg.REGISTERS[3], mycpu.myreg.REGISTERS[4], mycpu.myreg.REGISTERS[5], 
                          mycpu.myreg.REGISTERS[6], mycpu.myreg.REGISTERS[7]);
      // generate files needed to plot the waveform using GTKWave
      $dumpfile("cpu_wavedata.vcd");
      $dumpvars(0, testbenchCPU);
    end

    assign #2 INS = {INST_MEMORY[PC + 3], INST_MEMORY[PC + 2], INST_MEMORY[PC + 1], INST_MEMORY[PC]}; //fetching instruction
       
    initial
    begin
         // loadi 0 0x0A
        {INST_MEMORY[3],INST_MEMORY[2],INST_MEMORY[1],INST_MEMORY[0]}     = 32'b00000101_00000000_00000000_00001010;
        // mov 1 0
        {INST_MEMORY[7],INST_MEMORY[6],INST_MEMORY[5],INST_MEMORY[4]}     = 32'b00000100_00000001_00000000_00000000;
        // loadi 2 0x05
        {INST_MEMORY[11],INST_MEMORY[10],INST_MEMORY[9],INST_MEMORY[8]}   = 32'b00000101_00000010_00000000_00000101;
        // sub 3 1 2
        {INST_MEMORY[15],INST_MEMORY[14],INST_MEMORY[13],INST_MEMORY[12]} = 32'b00000001_00000011_00000001_00000010;
        // or 3 1 2
        {INST_MEMORY[19],INST_MEMORY[18],INST_MEMORY[17],INST_MEMORY[16]} = 32'b00000011_00000011_00000001_00000010;
        // and 3 1 2
        {INST_MEMORY[23],INST_MEMORY[22],INST_MEMORY[21],INST_MEMORY[20]} = 32'b00000010_00000011_00000001_00000010;
        // add 3 1 2
        {INST_MEMORY[27],INST_MEMORY[26],INST_MEMORY[25],INST_MEMORY[24]} = 32'b00000000_00000001_00000001_00000010;
        // j 
        {INST_MEMORY[31],INST_MEMORY[30],INST_MEMORY[29],INST_MEMORY[28]} = 32'b00000110_11111110_00000000_00000000;

        CLK = 1'b1;
        
        // assign values with time to input signals to see output 
        RESET = 1'b1;

        #1
        RESET = 1'b0;

        #37
        RESET = 1'b1;
        #4
        RESET = 1'b0;

        #200
        $finish;
    end
    
    // clock signal generation
    always
    begin
      #7 CLK = ~CLK;       
    end              

endmodule

Labs/Processor/Lab05/part04/cpu_wavedata.vcd
$date
	Fri May 15 11:42:45 2020
$end
$version
	Icarus Verilog
$end
$timescale
	1s
$end
$scope module testbenchCPU $end
$var wire 32 ! PC [31:0] $end
$var wire 32 " INS [31:0] $end
$var reg 1 # CLK $end
$var reg 1 $ RESET $end
$scope module mycpu $end
$var wire 8 % ALOP2 [7:0] $end
$var wire 1 & ANDOUTBEQ $end
$var wire 1 # CLK $end
$var wire 32 ' INSTRUCTION [31:0] $end
$var wire 1 $ RESET $end
$var wire 1 ( jumpMUXSEL $end
$var wire 1 ) twoscompMUXSEL $end
$var wire 1 * regWRITEEN $end
$var wire 1 + jump $end
$var wire 1 , immeMUXSEL $end
$var wire 1 - beq $end
$var wire 3 . aluOP [2:0] $end
$var wire 8 / TWOSMUXOUT [7:0] $end
$var wire 8 0 TWOSCOMPOUT [7:0] $end
$var wire 8 1 SOURCE2 [7:0] $end
$var wire 8 2 SOURCE1 [7:0] $end
$var wire 8 3 REGOUT2 [7:0] $end
$var wire 8 4 REGOUT1 [7:0] $end
$var wire 32 5 PCNEXT [31:0] $end
$var wire 32 6 PCJUMP [31:0] $end
$var wire 32 7 PCINCBY4 [31:0] $end
$var wire 8 8 OP [7:0] $end
$var wire 8 9 DESTINATION [7:0] $end
$var wire 8 : ALUOUT [7:0] $end
$var wire 1 ; ALUCOMP $end
$var wire 8 < ALOP1 [7:0] $end
$var reg 32 = PC [31:0] $end
$scope module jumpadder $end
$var wire 32 > INPUT2 [31:0] $end
$var wire 32 ? INPUT1 [31:0] $end
$var reg 32 @ RESULT [31:0] $end
$upscope $end
$scope module muximme $end
$var wire 8 A INPUT2 [7:0] $end
$var wire 1 , SELECT $end
$var wire 8 B INPUT1 [7:0] $end
$var reg 8 C RESULT [7:0] $end
$upscope $end
$scope module muxjump $end
$var wire 32 D INPUT2 [31:0] $end
$var wire 1 ( SELECT $end
$var wire 32 E INPUT1 [31:0] $end
$var reg 32 F RESULT [31:0] $end
$upscope $end
$scope module muxtwos $end
$var wire 1 ) SELECT $end
$var wire 8 G INPUT2 [7:0] $end
$var wire 8 H INPUT1 [7:0] $end
$var reg 8 I RESULT [7:0] $end
$upscope $end
$scope module myadder $end
$var wire 32 J INPUT1 [31:0] $end
$var wire 32 K INPUT2 [31:0] $end
$var reg 32 L RESULT [31:0] $end
$upscope $end
$scope module myalu $end
$var wire 1 ; COMP $end
$var wire 8 M DATA1 [7:0] $end
$var wire 8 N DATA2 [7:0] $end
$var wire 3 O SELECT [2:0] $end
$var reg 8 P RESULT [7:0] $end
$upscope $end
$scope module mycu $end
$var wire 1 Q ALUCOMP $end
$var wire 8 R OP [7:0] $end
$var wire 1 $ RESET $end
$var reg 3 S aluOP [2:0] $end
$var reg 1 - beq $end
$var reg 1 , immeMUXSEL $end
$var reg 1 + jump $end
$var reg 1 * regWRITEEN $end
$var reg 1 ) twoscompMUXSEL $end
$upscope $end
$scope module myreg $end
$var wire 1 # CLK $end
$var wire 8 T IN [7:0] $end
$var wire 3 U INADDRESS [2:0] $end
$var wire 8 V OUT1 [7:0] $end
$var wire 3 W OUT1ADDRESS [2:0] $end
$var wire 8 X OUT2 [7:0] $end
$var wire 3 Y OUT2ADDRESS [2:0] $end
$var wire 1 $ RESET $end
$var wire 1 * WRITE $end
$var integer 32 Z i [31:0] $end
$upscope $end
$scope module twos $end
$var wire 8 [ INPUT [7:0] $end
$var reg 8 \ RESULT [7:0] $end
$upscope $end
$upscope $end
$upscope $end
$enddefinitions $end
#0
$dumpvars
bx \
bx [
bx Z
bx Y
bx X
bx W
bx V
bx U
bx T
bx S
bx R
zQ
bx P
bx O
bx N
bx M
bx L
b100 K
b11111111111111111111111111111100 J
bx I
bx H
bx G
bx F
bx E
bx D
bx C
bx B
bx A
bx @
bx ?
bx00 >
b11111111111111111111111111111100 =
bx <
x;
bx :
bx 9
bx 8
bx 7
bx 6
bx 5
bx 4
bx 3
bx 2
bx 1
bx 0
bx /
bx .
0-
x,
0+
x*
x)
0(
bx '
0&
bx %
1$
1#
bx "
b11111111111111111111111111111100 !
$end
#1
0$
#2
b0 5
b0 F
b1000 Z
b0 7
b0 ?
b0 E
b0 L
#7
0#
#14
1#
#15
b0 !
b0 =
b0 J
#17
1;
b0 W
b0 :
b0 P
b0 T
b0 U
b0 2
b1010 <
b1010 C
b1010 N
b10 Y
b100 5
b100 F
b0 >
b0 9
b1010 1
b1010 A
b101 8
b101 R
b100 7
b100 ?
b100 E
b100 L
b101000000000000000000001010 "
b101000000000000000000001010 '
#18
b0 .
b0 O
b0 S
1*
1,
0)
#19
0;
b0 /
b0 B
b0 I
b0 0
b0 G
b0 \
b1010 :
b1010 P
b1010 T
b0 %
b0 M
b0 4
b0 V
b0 3
b0 H
b0 X
b0 [
b100 6
b100 @
b100 D
#21
0#
#28
1#
#29
b100 !
b100 =
b100 J
#31
b11 U
b11110 <
b11110 C
b11110 N
b110 Y
b1000 5
b1000 F
b1100 >
b11 9
b11110 1
b11110 A
b1000 7
b1000 ?
b1000 E
b1000 L
b101000000110000000000011110 "
b101000000110000000000011110 '
#32
b11110 :
b11110 P
b11110 T
b1010 %
b1010 M
b1010 4
b1010 V
#33
b10100 6
b10100 @
b10100 D
#35
0#
#42
1#
#43
b1000 !
b1000 =
b1000 J
#45
b1 U
b101 <
b101 C
b101 N
b101 Y
b1100 5
b1100 F
b100 >
b1 9
b101 1
b101 A
b1100 7
b1100 ?
b1100 E
b1100 L
b101000000010000000000000101 "
b101000000010000000000000101 '
#46
b101 :
b101 P
b101 T
#47
b10000 6
b10000 @
b10000 D
#49
0#
#56
1#
#57
b1100 !
b1100 =
b1100 J
#59
b0 U
b1 <
b1 C
b1 N
b1 Y
b10000 5
b10000 F
b0 >
b0 9
b1 1
b1 A
b0 8
b0 R
b10000 7
b10000 ?
b10000 E
b10000 L
b1 "
b1 '
#60
1;
b0 <
b0 C
b0 N
b1 :
b1 P
b1 T
b1 .
b1 O
b1 S
0,
#61
b101 <
b101 C
b101 N
b101 /
b101 B
b101 I
b11111011 0
b11111011 G
b11111011 \
b101 3
b101 H
b101 X
b101 [
#62
0;
b1111 :
b1111 P
b1111 T
#63
0#
#70
1#
#71
b10000 !
b10000 =
b10000 J
#73
b1 U
b11 Y
b10100 5
b10100 F
b100 >
b1 9
b11 1
b11 A
b111 8
b111 R
b10100 7
b10100 ?
b10100 E
b10100 L
b111000000010000000000000011 "
b111000000010000000000000011 '
#74
b11111011 <
b11111011 C
b11111011 N
b11111011 /
b11111011 B
b11111011 I
1-
0*
1)
b1111 %
b1111 M
b1111 4
b1111 V
#75
b11100010 <
b11100010 C
b11100010 N
b11100010 /
b11100010 B
b11100010 I
b11100010 0
b11100010 G
b11100010 \
b11110 3
b11110 H
b11110 X
b11110 [
b11000 6
b11000 @
b11000 D
#76
b10100 5
b10100 F
0(
0&
0;
b11110001 :
b11110001 P
b11110001 T
#77
0#
#84
1#
#85
b10100 !
b10100 =
b10100 J
#87
b101 U
b0 Y
b11000 5
b11000 F
b11111111111111111111111111110100 >
b11111101 9
b0 1
b0 A
b110 8
b110 R
b11000 7
b11000 ?
b11000 E
b11000 L
b110111111010000000000000000 "
b110111111010000000000000000 '
#88
1(
0-
1+
#89
b11110001 <
b11110001 C
b11110001 N
b11110001 /
b11110001 B
b11110001 I
b11110001 0
b11110001 G
b11110001 \
b1100 5
b1100 F
b1111 3
b1111 H
b1111 X
b1111 [
b1100 6
b1100 @
b1100 D
#91
1;
b0 :
b0 P
b0 T
0#
#98
1#
#99
b1100 !
b1100 =
b1100 J
#101
b0 U
b1 Y
b0 >
b0 9
b1 1
b1 A
b0 8
b0 R
b10000 7
b10000 ?
b10000 E
b10000 L
b1 "
b1 '
#102
b10000 5
b10000 F
b1111 <
b1111 C
b1111 N
0(
b1111 /
b1111 B
b1111 I
0+
1*
0)
#103
b101 <
b101 C
b101 N
b101 /
b101 B
b101 I
b11111011 0
b11111011 G
b11111011 \
b101 3
b101 H
b101 X
b101 [
b10000 6
b10000 @
b10000 D
#104
0;
b10100 :
b10100 P
b10100 T
#105
0#
#112
1#
#113
b10000 !
b10000 =
b10000 J
#115
b1 U
b11 Y
b10100 5
b10100 F
b100 >
b1 9
b11 1
b11 A
b111 8
b111 R
b10100 7
b10100 ?
b10100 E
b10100 L
b111000000010000000000000011 "
b111000000010000000000000011 '
#116
b11111011 <
b11111011 C
b11111011 N
b11111011 /
b11111011 B
b11111011 I
1-
0*
1)
b10100 %
b10100 M
b10100 4
b10100 V
#117
b11100010 <
b11100010 C
b11100010 N
b11100010 /
b11100010 B
b11100010 I
b11100010 0
b11100010 G
b11100010 \
b11110 3
b11110 H
b11110 X
b11110 [
b11000 6
b11000 @
b11000 D
#118
b11110110 :
b11110110 P
b11110110 T
#119
0#
#126
1#
#127
b10100 !
b10100 =
b10100 J
#129
b101 U
b0 Y
b11000 5
b11000 F
b11111111111111111111111111110100 >
b11111101 9
b0 1
b0 A
b110 8
b110 R
b11000 7
b11000 ?
b11000 E
b11000 L
b110111111010000000000000000 "
b110111111010000000000000000 '
#130
1(
0-
1+
#131
b11101100 <
b11101100 C
b11101100 N
b11101100 /
b11101100 B
b11101100 I
b11101100 0
b11101100 G
b11101100 \
b1100 5
b1100 F
b10100 3
b10100 H
b10100 X
b10100 [
b1100 6
b1100 @
b1100 D
#133
1;
b0 :
b0 P
b0 T
0#
#140
1#
#141
b1100 !
b1100 =
b1100 J
#143
b0 U
b1 Y
b0 >
b0 9
b1 1
b1 A
b0 8
b0 R
b10000 7
b10000 ?
b10000 E
b10000 L
b1 "
b1 '
#144
b10000 5
b10000 F
b10100 <
b10100 C
b10100 N
0(
b10100 /
b10100 B
b10100 I
0+
1*
0)
#145
b101 <
b101 C
b101 N
b101 /
b101 B
b101 I
b11111011 0
b11111011 G
b11111011 \
b101 3
b101 H
b101 X
b101 [
b10000 6
b10000 @
b10000 D
#146
0;
b11001 :
b11001 P
b11001 T
#147
0#
#154
1#
#155
b10000 !
b10000 =
b10000 J
#157
b1 U
b11 Y
b10100 5
b10100 F
b100 >
b1 9
b11 1
b11 A
b111 8
b111 R
b10100 7
b10100 ?
b10100 E
b10100 L
b111000000010000000000000011 "
b111000000010000000000000011 '
#158
b11111011 <
b11111011 C
b11111011 N
b11111011 /
b11111011 B
b11111011 I
1-
0*
1)
b11001 %
b11001 M
b11001 4
b11001 V
#159
b11100010 <
b11100010 C
b11100010 N
b11100010 /
b11100010 B
b11100010 I
b11100010 0
b11100010 G
b11100010 \
b11110 3
b11110 H
b11110 X
b11110 [
b11000 6
b11000 @
b11000 D
#160
b11111011 :
b11111011 P
b11111011 T
#161
0#
#168
1#
#169
b10100 !
b10100 =
b10100 J
#171
b101 U
b0 Y
b11000 5
b11000 F
b11111111111111111111111111110100 >
b11111101 9
b0 1
b0 A
b110 8
b110 R
b11000 7
b11000 ?
b11000 E
b11000 L
b110111111010000000000000000 "
b110111111010000000000000000 '
#172
1(
0-
1+
#173
b11100111 <
b11100111 C
b11100111 N
b11100111 /
b11100111 B
b11100111 I
b11100111 0
b11100111 G
b11100111 \
b1100 5
b1100 F
b11001 3
b11001 H
b11001 X
b11001 [
b1100 6
b1100 @
b1100 D
#175
1;
b0 :
b0 P
b0 T
0#
#182
1#
#183
b1100 !
b1100 =
b1100 J
#185
b0 U
b1 Y
b0 >
b0 9
b1 1
b1 A
b0 8
b0 R
b10000 7
b10000 ?
b10000 E
b10000 L
b1 "
b1 '
#186
b10000 5
b10000 F
b11001 <
b11001 C
b11001 N
0(
b11001 /
b11001 B
b11001 I
0+
1*
0)
#187
b101 <
b101 C
b101 N
b101 /
b101 B
b101 I
b11111011 0
b11111011 G
b11111011 \
b101 3
b101 H
b101 X
b101 [
b10000 6
b10000 @
b10000 D
#188
0;
b11110 :
b11110 P
b11110 T
#189
0#
#196
1#
#197
b10000 !
b10000 =
b10000 J
#199
b1 U
b11 Y
b10100 5
b10100 F
b100 >
b1 9
b11 1
b11 A
b111 8
b111 R
b10100 7
b10100 ?
b10100 E
b10100 L
b111000000010000000000000011 "
b111000000010000000000000011 '
#200
b11111011 <
b11111011 C
b11111011 N
b11111011 /
b11111011 B
b11111011 I
1-
0*
1)
b11110 %
b11110 M
b11110 4
b11110 V
#201
b11100010 <
b11100010 C
b11100010 N
b11100010 /
b11100010 B
b11100010 I
b11100010 0
b11100010 G
b11100010 \
b11110 3
b11110 H
b11110 X
b11110 [
b11000 6
b11000 @
b11000 D
#202
b11000 5
b11000 F
1(
1&
1;
b0 :
b0 P
b0 T
#203
0#
#210
1#
#211
b11000 !
b11000 =
b11000 J
#213
bx W
bx U
bx 2
bx Y
bx00 >
bx 9
bx 1
bx A
bx 8
bx R
b11100 7
b11100 ?
b11100 E
b11100 L
bx "
bx '
#215
bx <
bx C
bx N
bx /
bx B
bx I
bx 0
bx G
bx \
bx 5
bx F
bx %
bx M
bx 4
bx V
bx 3
bx H
bx X
bx [
bx 6
bx @
bx D
#217
x(
x&
x;
bx :
bx P
bx T
0#
#224
1#
#225
bx !
bx =
bx J
#227
bx 7
bx ?
bx E
bx L
