Labs/Processor/Lab06/part02/cache_memory/data_memory.v
/*
Program	: 256x8-bit data memory (4-Byte blocks)
Author	: Isuru Nawinne
Date    : 30/05/2020

Description	:

This program presents a primitive data memory module for CO224 Lab 6 - Part 2
This memory allows data to be read and written as 4-Byte blocks
*/

module data_memory(
	clock,
    reset,
    read,
    write,
    address,
    writedata,
    readdata,
	busywait
);
input				clock;
input           	reset;
input           	read;
input           	write;
input[5:0]      	address;
input[31:0]     	writedata;
output reg [31:0]	readdata;
output reg      	busywait;

//Declare memory array 256x8-bits 
reg [7:0] memory_array [255:0];

//Detecting an incoming memory access
reg readaccess, writeaccess;
always @(read, write)
begin
	busywait = (read || write)? 1 : 0;
	readaccess = (read && !write)? 1 : 0;
	writeaccess = (!read && write)? 1 : 0;
end

//Reading & writing
always @(posedge clock)
begin
	if(readaccess)
	begin
		readdata[7:0]   = #40 memory_array[{address,2'b00}];
		readdata[15:8]  = #40 memory_array[{address,2'b01}];
		readdata[23:16] = #40 memory_array[{address,2'b10}];
		readdata[31:24] = #40 memory_array[{address,2'b11}];
		busywait = 0;
		readaccess = 0;
	end
	if(writeaccess)
	begin
		memory_array[{address,2'b00}] = #40 writedata[7:0];
		memory_array[{address,2'b01}] = #40 writedata[15:8];
		memory_array[{address,2'b10}] = #40 writedata[23:16];
		memory_array[{address,2'b11}] = #40 writedata[31:24];
		busywait = 0;
		writeaccess = 0;
	end
end

//Reset memory
always @(posedge reset)
begin
    if (reset)
    begin
        for (i=0;i<256; i=i+1)
            memory_array[i] = 0;
        
        busywait = 0;
		readaccess = 0;
		writeaccess = 0;
    end
end

endmodule

Labs/Processor/Lab06/part02/cache_memory/cache_memory.v
`include "data_memory.v"

module cache_memory(
	clock,
    reset,
    read,
    write,
    address,
    writedata,
    readdata,
	busywait
);
    input				clock;
    input           	reset;
    input           	read;
    input           	write;
    input[7:0]      	address;
    input[7:0]     	    writedata;
    output reg [7:0]	readdata;
    output reg      	busywait;

    //Declare cache memory array 256x8-bits 
    reg [31:0] data_array [8:0];
    //Declare tag array 256x8-bits 
    reg [2:0] tag_array [8:0];
    //Declare valid bit array 256x8-bits 
    reg [1:0] dirtyBit_array [8:0];
    //Declare valid bit array 256x8-bits 
    reg [1:0] validBit_array [8:0];

    parameter IDLE = 2'b00, MEM_READ = 2'b01, MEM_WRITE = 2'b10;
    reg [1:0] state, next_state;

    // variables to handle state changes
    reg CURRENT_DIRTY, CURRENT_VALID, TAG_MATCH;
    reg [2:0] CURRENT_TAG;
    reg [31:0] CURRENT_DATA;

    // tempory variable to hold the data from the cache
    reg [7:0] tempory_data;

    // variables to hold the values of the memory module
    reg MAIN_MEM_READ, MAIN_MEM_WRITE;
    reg [5:0] MAIN_MEM_ADDRESS;
    reg [31:0] MAIN_MEM_WRITE_DATA;
    wire [31:0] MAIN_MEM_READ_DATA;
    wire MAIN_MEM_BUSY_WAIT;

    //initiating the memory module
    data_memory myDataMem (clock, reset, MAIN_MEM_READ, MAIN_MEM_WRITE, MAIN_MEM_ADDRESS,
            MAIN_MEM_WRITE_DATA, MAIN_MEM_READ_DATA, MAIN_MEM_BUSY_WAIT);

    // decoding the address
    wire [2:0] tag, index;
    wire [1:0] offset;
    assign tag = address[7:5];
    assign index = address[4:2];
    assign offset = address[1:0];

    //Detecting an incoming memory access
    reg readaccess, writeaccess;
    always @(read, write)
    begin
        busywait = (read || write)? 1 : 0;
        readaccess = (read && !write)? 1 : 0;
        writeaccess = (!read && write)? 1 : 0;
    end

    // combinational next state logic
    always @(*)
    begin
        case (state)
            IDLE:
                if (!CURRENT_VALID && (readaccess || writeaccess)) 
                    next_state = MEM_READ;
                else if (CURRENT_VALID && TAG_MATCH && (readaccess || writeaccess))
                    next_state = IDLE;
                else if (CURRENT_VALID && !CURRENT_DIRTY && !TAG_MATCH && (readaccess || writeaccess))
                    next_state = MEM_READ;
                else if (CURRENT_VALID && CURRENT_DIRTY && !TAG_MATCH && (readaccess || writeaccess))
                    next_state = MEM_WRITE;
            
            MEM_READ:
                if (MAIN_MEM_BUSY_WAIT)
                    next_state = MEM_READ;
                else    
                    begin
                        next_state = IDLE;
                        // put the read data to the cache
                        data_array[index] = MAIN_MEM_READ_DATA;
                        tag_array[index] = tag;
                        validBit_array[index] = 1'b1; // set the valid bit after loading data
                        dirtyBit_array[index] = 1'b0; // set the dirty bit after loading data
                    end


            MEM_WRITE:
                if (MAIN_MEM_BUSY_WAIT)
                    next_state = MEM_WRITE;
                else   
                    begin 
                        //next_state = IDLE;
                        validBit_array[index] = 1'b1; // set the valid bit after loading data
                        dirtyBit_array[index] = 1'b0; // set the valid bit after writing data

                        if (CURRENT_VALID && !TAG_MATCH)
                            next_state = MEM_READ;
                        else
                            next_state = IDLE;
                    end
            
        endcase
    end

    // TODO: Delays should be corrected
    // combinational output logic
    always @(*)
    begin
        case(state)
            IDLE:
            begin
                // set main memory read and write signal to low
                MAIN_MEM_READ = 1'b0;
                MAIN_MEM_WRITE = 1'b0;               
                
                #1 // loading the current values
                CURRENT_VALID = validBit_array[index];
                CURRENT_DIRTY = dirtyBit_array[index];
                CURRENT_DATA  = data_array[index];
                CURRENT_TAG   = tag_array[index];

                #1
                if (CURRENT_TAG == tag) // tag comparisan
                    TAG_MATCH = 1'b1;
                else
                    TAG_MATCH = 1'b0;

                if (readaccess) // detect the idle read status
                begin
                  // fetching data
                  case(offset)
                    2'b00:
                        tempory_data = data_array[index][7:0];
                    2'b01:
                        tempory_data = data_array[index][15:8];
                    2'b10:
                        tempory_data = data_array[index][23:16];
                    2'b11:
                        tempory_data = data_array[index][31:24];
                  endcase
                  
                  if (TAG_MATCH && CURRENT_VALID)
                  begin
                    busywait = 1'b0; // set the busy wait signal to zero
                    readdata = tempory_data; // output the data
                  end
                end

                if (writeaccess && TAG_MATCH && CURRENT_VALID) // detect the idle write status
                begin
                  #1
                  case(offset) // writing to the register
                    2'b00:
                        data_array[index][7:0] = writedata;
                    2'b01:
                        data_array[index][15:8] = writedata;
                    2'b10:
                        data_array[index][23:16] = writedata;
                    2'b11:
                        data_array[index][31:24] = writedata;
                  endcase

                  dirtyBit_array[index] = 1'b1; // set the dirty bit because data is not consistant with the memory
                  
                  busywait = 1'b0; // set the busy wait signal to zero
                end
                
            end
         
            MEM_READ: 
            begin
                MAIN_MEM_READ = 1'b1;
                MAIN_MEM_WRITE = 1'b0;
                // set the address to teh main memory
                MAIN_MEM_ADDRESS = {tag, index};
            end

            MEM_WRITE: 
            begin
                MAIN_MEM_READ = 1'b0;
                MAIN_MEM_WRITE = 1'b1;
                // set the address to the main memory
                MAIN_MEM_ADDRESS = tag_array[index];
                // set data to be written
                MAIN_MEM_WRITE_DATA = data_array[index];
            end
            
        endcase
    end

    integer i;

    // sequential logic for state transitioning 
    always @(posedge reset)
    begin
        if(reset)
        begin
            for (i=0;i<8; i=i+1) // resetting the registers
                begin
                    data_array[i] = 0;
                    validBit_array[i] = 0;
                    dirtyBit_array[i] = 0;
                end
        end
    end

    // state change logic
    always @ (posedge clock)
    begin
        if (!reset)
            state = next_state;
        else
            state = IDLE;
    end

    /* Cache Controller FSM End */

endmodule

Labs/Processor/Lab06/part02/cache_memory/testbenchCPU.v
/*
Author - W M D U Thilakarathna
Reg No - E/16/366
*/

`include "cache_memory.v"

module testbenchCPU;
    
    //input registers
    wire [31:0] INS;
    reg CLK, RESET; 
    reg [7:0] INST_MEMORY [1023:0] ; //instruction array

    wire[31:0] PC;

    reg memReadEn, memWriteEn; // memory read or write enable signals
    reg [7:0] ADDRESS; // address of the data memory
    reg [7:0] WRITE_DATA; // read and write data of the memory module
    wire [7:0] READ_DATA;
    wire BUSY_WAIT; // busy wait signal of the CPU
    
    cache_memory myCacheMemory(CLK, RESET, memReadEn, memWriteEn, ADDRESS, WRITE_DATA, READ_DATA, BUSY_WAIT); // initialize the memory module

    initial // instruction array
    begin
      //monitor command to check the content od the register file
      /*
      $monitor($time, " REG0: %b  REG1: %b  REG2: %b  REG3: %b  REG4: %b  REG5: %b  REG6: %b  REG7: %b ",
                          mycpu.myreg.REGISTERS[0], mycpu.myreg.REGISTERS[1], mycpu.myreg.REGISTERS[2], 
                          mycpu.myreg.REGISTERS[3], mycpu.myreg.REGISTERS[4], mycpu.myreg.REGISTERS[5], 
                          mycpu.myreg.REGISTERS[6], mycpu.myreg.REGISTERS[7]);
      */
      // generate files needed to plot the waveform using GTKWave
      $dumpfile("cache_wavedata.vcd");
      $dumpvars(0, testbenchCPU);
    end
        
    initial
    begin
        CLK = 1'b1;
        
        // assign values with time to input signals to see output 
        RESET = 1'b1;

        #1
        RESET = 1'b0;
        
        /*
        #1
        ADDRESS = 8'b0000_0001;
        memReadEn = 1'b1;       
        memWriteEn = 1'b0;

        #200 
        ADDRESS = 8'b0000_0010;
        memReadEn = 1'b0;

        #5
        memReadEn = 1'b1;

        #10
        ADDRESS = 8'b1000_0010;
        */

        
        #1
        ADDRESS = 8'b0000_0001;
        WRITE_DATA = 8'hFA;
        memReadEn = 1'b0;       
        memWriteEn = 1'b1;

        #200 
        ADDRESS = 8'b0000_0001;
        memReadEn = 1'b1;
        memWriteEn = 1'b0;

        #30
        ADDRESS = 8'b0010_0001;
        WRITE_DATA = 8'hFA;
        memReadEn = 1'b0;       
        memWriteEn = 1'b1;
        

        #800
        $finish;
    end
    
    // clock signal generation
    always
    begin
      #4 CLK = ~CLK;
    end              

endmodule

Labs/Processor/Lab06/part02/cache_memory/cache_wavedata.vcd
$date
	Sun Jun  7 14:10:28 2020
$end
$version
	Icarus Verilog
$end
$timescale
	1s
$end
$scope module testbenchCPU $end
$var wire 8 ! READ_DATA [7:0] $end
$var wire 1 " BUSY_WAIT $end
$var reg 8 # ADDRESS [7:0] $end
$var reg 1 $ CLK $end
$var reg 1 % RESET $end
$var reg 8 & WRITE_DATA [7:0] $end
$var reg 1 ' memReadEn $end
$var reg 1 ( memWriteEn $end
$scope module myCacheMemory $end
$var wire 8 ) address [7:0] $end
$var wire 1 $ clock $end
$var wire 1 ' read $end
$var wire 1 % reset $end
$var wire 1 ( write $end
$var wire 8 * writedata [7:0] $end
$var wire 3 + tag [2:0] $end
$var wire 2 , offset [1:0] $end
$var wire 3 - index [2:0] $end
$var wire 32 . MAIN_MEM_READ_DATA [31:0] $end
$var wire 1 / MAIN_MEM_BUSY_WAIT $end
$var reg 32 0 CURRENT_DATA [31:0] $end
$var reg 1 1 CURRENT_DIRTY $end
$var reg 3 2 CURRENT_TAG [2:0] $end
$var reg 1 3 CURRENT_VALID $end
$var reg 6 4 MAIN_MEM_ADDRESS [5:0] $end
$var reg 1 5 MAIN_MEM_READ $end
$var reg 1 6 MAIN_MEM_WRITE $end
$var reg 32 7 MAIN_MEM_WRITE_DATA [31:0] $end
$var reg 1 8 TAG_MATCH $end
$var reg 1 " busywait $end
$var reg 2 9 next_state [1:0] $end
$var reg 1 : readaccess $end
$var reg 8 ; readdata [7:0] $end
$var reg 2 < state [1:0] $end
$var reg 8 = tempory_data [7:0] $end
$var reg 1 > writeaccess $end
$var integer 32 ? i [31:0] $end
$scope module myDataMem $end
$var wire 6 @ address [5:0] $end
$var wire 1 $ clock $end
$var wire 1 5 read $end
$var wire 1 % reset $end
$var wire 1 6 write $end
$var wire 32 A writedata [31:0] $end
$var reg 1 / busywait $end
$var reg 1 B readaccess $end
$var reg 32 C readdata [31:0] $end
$var reg 1 D writeaccess $end
$var integer 32 E i [31:0] $end
$upscope $end
$upscope $end
$upscope $end
$enddefinitions $end
#0
$dumpvars
b100000000 E
0D
bx C
0B
bx A
bx @
b1000 ?
x>
bx =
b0 <
bx ;
x:
bx 9
x8
bx 7
06
05
bx 4
x3
bx 2
x1
bx 0
0/
bx .
bx -
bx ,
bx +
bx *
bx )
x(
x'
bx &
1%
1$
bx #
x"
bx !
$end
#1
0%
#2
1>
0:
1"
b0 +
b0 -
b1 ,
08
1(
0'
b11111010 &
b11111010 *
b1 #
b1 )
#3
b1 9
b0 0
01
03
#4
0$
#8
1B
1/
b0 4
b0 @
15
b1 9
b1 <
1$
#12
0$
#16
1$
#20
0$
#24
1$
#28
0$
#32
1$
#36
0$
#40
1$
#44
0$
#48
1$
#52
0$
#56
1$
bx00000000 .
bx00000000 C
#60
0$
#64
1$
#68
0$
#72
1$
#76
0$
#80
1$
#84
0$
#88
1$
#92
0$
#96
1$
bx0000000000000000 .
bx0000000000000000 C
#100
0$
#104
1$
#108
0$
#112
1$
#116
0$
#120
1$
#124
0$
#128
1$
#132
0$
#136
1$
bx111111110000000000000000 .
bx111111110000000000000000 C
#140
0$
#144
1$
#148
0$
#152
1$
#156
0$
#160
1$
#164
0$
#168
1$
#172
0$
#176
05
b0 <
b1 9
1$
0B
0/
b111111110000000000000000 .
b111111110000000000000000 C
#177
b0 2
b111111110000000000000000 0
13
#178
b0 9
18
#179
0"
#180
0$
#184
1$
#188
0$
#192
1$
#196
0$
#200
1$
#202
0>
1:
1"
0(
1'
#203
b111111111111101000000000 0
11
#204
b11111010 !
b11111010 ;
0"
b11111010 =
0$
#208
1$
#212
0$
#216
1$
#220
0$
#224
1$
#228
0$
#232
1>
0:
1"
b1 +
1$
1(
0'
b100001 #
b100001 )
#234
b10 9
08
#236
0$
#240
1D
1/
b111111111111101000000000 7
b111111111111101000000000 A
16
b10 9
b10 <
1$
