Labs/Processor/Lab05/part02/reg_file.v
module reg_file(IN, OUT1, OUT2, INADDRESS, OUT1ADDRESS, OUT2ADDRESS, WRITE, CLK, RESET);

input [7:0] IN;  // 8 bit data input
input [2:0] INADDRESS, OUT1ADDRESS, OUT2ADDRESS; // 3 bit data inputs
input WRITE, CLK, RESET; // 1 bit data inputs
output [7:0] OUT1, OUT2; // 8 bit data outputs

reg [7:0] OUT1, OUT2; // registers for the output

reg [7:0] registers [7:0]; // 8x8 register file

reg [7:0] OUT1CURR, OUT2CURR; //take the current value of the output to give after delay

integer i;

always @ (posedge CLK) // this code block run when we are in a positive clock edge
begin
    // write input to the in address
    if (WRITE == 1)
        #2 registers[INADDRESS] = IN;     
end


//always run if out1 address or out2 address or their data changed
always @ (OUT1ADDRESS or OUT2ADDRESS or registers[OUT1ADDRESS] or registers[OUT2ADDRESS])
begin
    if (RESET == 0)
    begin
        #2
        OUT1 = registers[OUT1ADDRESS]; //writing data to outputs
        OUT2 = registers[OUT2ADDRESS];  
    end
       
end

// combinational logic output for reset signal (level triggered input)
always @ (*)
begin
    if (RESET == 1)
    begin
        #2 
        for (i = 0; i < 8; i++) //looping through register file and setting them to 0s
        begin
            registers[i] = 0;
        end   

        // after reseting writing for the outputs
        #2    
        OUT1 = registers[OUT1ADDRESS]; 
        OUT2 = registers[OUT2ADDRESS]; 
    end
    
end

endmodule

Labs/Processor/Lab05/part02/testbench.v
`include "reg_file.v"

module reg_file_tb;
    
    //input registers
    reg [7:0] WRITEDATA;
    reg [2:0] WRITEREG, READREG1, READREG2;
    reg CLK, RESET, WRITEENABLE; 
    wire [7:0] REGOUT1, REGOUT2;
    
    reg_file myregfile(WRITEDATA, REGOUT1, REGOUT2, WRITEREG, READREG1, READREG2, WRITEENABLE, CLK, RESET);
       
    initial
    begin
        CLK = 1'b1;
        
        // generate files needed to plot the waveform using GTKWave
        $dumpfile("reg_file_wavedata_my.vcd");
		$dumpvars(0, reg_file_tb);
        
        // assign values with time to input signals to see output 
        RESET = 1'b0;
        WRITEENABLE = 1'b0;

        #2
        READREG1 = 3'd0;
        READREG2 = 3'd1;

        #2
        RESET = 1'b1;

        #5
        READREG1 = 3'd2;
        READREG2 = 3'd3;

        #4
        RESET = 1'b0;  
        WRITEENABLE = 1'b1;  

        #1
        WRITEREG = 3'd2;
        WRITEDATA = 8'd95;        
        
        #9
        WRITEENABLE = 1'b0;     

        #4
        WRITEREG = 3'd3;
        WRITEDATA = 8'd50;  

        #5
        WRITEENABLE = 1'b1;

        #10
        WRITEENABLE = 1'b0;

        #6
        READREG1 = 3'd4;
        READREG2 = 3'd5;
        WRITEDATA = 8'd45;
        WRITEREG = 3'd5;

        #1
        WRITEENABLE = 1'b1;

        #3
        WRITEENABLE = 1'b0;

        #6
        RESET = 1'b1;

        #6
        RESET = 1'b0;

        
        #20
        $finish;
    end
    
    // clock signal generation
    always
        #5 CLK = ~CLK;
        

endmodule

Labs/Processor/Lab05/part02/reg_file_wavedata_my.vcd
$date
	Sun May  3 18:25:25 2020
$end
$version
	Icarus Verilog
$end
$timescale
	1s
$end
$scope module reg_file_tb $end
$var wire 8 ! REGOUT2 [7:0] $end
$var wire 8 " REGOUT1 [7:0] $end
$var reg 1 # CLK $end
$var reg 3 $ READREG1 [2:0] $end
$var reg 3 % READREG2 [2:0] $end
$var reg 1 & RESET $end
$var reg 8 ' WRITEDATA [7:0] $end
$var reg 1 ( WRITEENABLE $end
$var reg 3 ) WRITEREG [2:0] $end
$scope module myregfile $end
$var wire 1 # CLK $end
$var wire 8 * IN [7:0] $end
$var wire 3 + INADDRESS [2:0] $end
$var wire 8 , OUT1 [7:0] $end
$var wire 3 - OUT1ADDRESS [2:0] $end
$var wire 8 . OUT2 [7:0] $end
$var wire 3 / OUT2ADDRESS [2:0] $end
$var wire 1 & RESET $end
$var wire 1 ( WRITE $end
$var integer 32 0 i [31:0] $end
$upscope $end
$upscope $end
$enddefinitions $end
#0
$dumpvars
bx 0
bx /
bx .
bx -
bx ,
bx +
bx *
bx )
0(
bx '
0&
bx %
bx $
1#
bx "
bx !
$end
#2
b1 %
b1 /
b0 $
b0 -
#4
1&
#5
0#
#6
b1000 0
#8
b0 !
b0 .
b0 "
b0 ,
#9
b11 %
b11 /
b10 $
b10 -
#10
1#
#13
1(
0&
#14
b1011111 '
b1011111 *
b10 )
b10 +
#15
0#
#20
1#
#23
0(
#24
b1011111 "
b1011111 ,
#25
0#
#27
b110010 '
b110010 *
b11 )
b11 +
#30
1#
#32
1(
#35
0#
#40
1#
#42
0(
#44
b110010 !
b110010 .
#45
0#
#48
b101 )
b101 +
b101101 '
b101101 *
b101 %
b101 /
b100 $
b100 -
#49
1(
#50
b0 !
b0 .
b0 "
b0 ,
1#
#52
0(
#54
b101101 !
b101101 .
#55
0#
#58
1&
#60
b1000 0
1#
#62
b0 !
b0 .
#64
0&
