Labs/Processor/Lab05/part02/reg_file.v
module reg_file(IN, OUT1, OUT2, INADDRESS, OUT1ADDRESS, OUT2ADDRESS, WRITE, CLK, RESET);

input [7:0] IN;  // 8 bit data input
input [2:0] INADDRESS, OUT1ADDRESS, OUT2ADDRESS; // 3 bit data inputs
input WRITE, CLK, RESET; // 1 bit data inputs
output [7:0] OUT1, OUT2; // 8 bit data outputs

reg [7:0] OUT1, OUT2; // registers for the output

reg [7:0] registers [7:0]; // 8x8 register file

reg [7:0] OUT1CURR, OUT2CURR; //take the current value of the output to give after delay

integer i;

always @ (posedge CLK) // this code block run when we are in a positive clock edge
begin
    // write input to the in address
    if (WRITE == 1)
        #2 registers[INADDRESS] = IN;     
end


//always run if out1 address or out2 address or their data changed
always @ (OUT1ADDRESS or OUT2ADDRESS or registers[OUT1ADDRESS] or registers[OUT2ADDRESS])
begin
    if (RESET == 0)
    begin
        #2
        OUT1 = registers[OUT1ADDRESS]; //writing data to outputs
        OUT2 = registers[OUT2ADDRESS];  
    end
       
end

// combinational logic output for reset signal (level triggered input)
always @ (*)
begin
    if (RESET == 1)
    begin
        #2 
        for (i = 0; i < 8; i++) //looping through register file and setting them to 0s
        begin
            registers[i] = 0;
        end   

        // after reseting writing for the outputs
        #2    
        OUT1 = registers[OUT1ADDRESS]; 
        OUT2 = registers[OUT2ADDRESS]; 
    end
    
end

endmodule

Labs/Processor/Lab05/part02/reg_file_tb.v
// Computer Architecture (CO224) - Lab 05
// Design: Register File Testbench of Simple Processor
// Author: Kisaru Liyanage
// Date	: 30-April-2020
`include "reg_file.v"

module reg_file_tb;
    
    reg [7:0] WRITEDATA;
    reg [2:0] WRITEREG, READREG1, READREG2;
    reg CLK, RESET, WRITEENABLE; 
    wire [7:0] REGOUT1, REGOUT2;
    
    reg_file myregfile(WRITEDATA, REGOUT1, REGOUT2, WRITEREG, READREG1, READREG2, WRITEENABLE, CLK, RESET);
       
    initial
    begin
        CLK = 1'b1;
        
        // generate files needed to plot the waveform using GTKWave
        $dumpfile("reg_file_wavedata_my.vcd");
		$dumpvars(0, reg_file_tb);
        
        // assign values with time to input signals to see output 
        RESET = 1'b0;
        WRITEENABLE = 1'b0;
        
        #1
        RESET = 1'b1;
        READREG1 = 3'd0;
        READREG2 = 3'd4;
        
        #8
        RESET = 1'b0;
        
        #5
        WRITEREG = 3'd2;
        WRITEDATA = 8'd95;
        WRITEENABLE = 1'b1;
        
        #10
        WRITEENABLE = 1'b0;
        
        #1
        READREG1 = 3'd2;
        
        #9
        WRITEREG = 3'd1;
        WRITEDATA = 8'd28;
        WRITEENABLE = 1'b1;
        READREG1 = 3'd1;
        
        #10
        WRITEENABLE = 1'b0;
        
        #10
        WRITEREG = 3'd4;
        WRITEDATA = 8'd6;
        WRITEENABLE = 1'b1;
        
        #10
        WRITEDATA = 8'd15;
        WRITEENABLE = 1'b1;
        
        #10
        WRITEENABLE = 1'b0;
        
        #6
        WRITEREG = 3'd1;
        WRITEDATA = 8'd50;
        WRITEENABLE = 1'b1;
        
        #5
        WRITEENABLE = 1'b0;
        
        #10
        $finish;
    end
    
    // clock signal generation
    always
        #5 CLK = ~CLK;
        

endmodule

Labs/Processor/Lab05/part02/reg_file_wavedata_my.vcd
$date
	Fri May  1 13:13:22 2020
$end
$version
	Icarus Verilog
$end
$timescale
	1s
$end
$scope module reg_file_tb $end
$var wire 8 ! REGOUT2 [7:0] $end
$var wire 8 " REGOUT1 [7:0] $end
$var reg 1 # CLK $end
$var reg 3 $ READREG1 [2:0] $end
$var reg 3 % READREG2 [2:0] $end
$var reg 1 & RESET $end
$var reg 8 ' WRITEDATA [7:0] $end
$var reg 1 ( WRITEENABLE $end
$var reg 3 ) WRITEREG [2:0] $end
$scope module myregfile $end
$var wire 1 # CLK $end
$var wire 8 * IN [7:0] $end
$var wire 3 + INADDRESS [2:0] $end
$var wire 3 , OUT1ADDRESS [2:0] $end
$var wire 3 - OUT2ADDRESS [2:0] $end
$var wire 1 & RESET $end
$var wire 1 ( WRITE $end
$var reg 8 . OUT1 [7:0] $end
$var reg 8 / OUT2 [7:0] $end
$var integer 32 0 i [31:0] $end
$upscope $end
$upscope $end
$enddefinitions $end
#0
$dumpvars
bx 0
bx /
bx .
bx -
bx ,
bx +
bx *
bx )
0(
bx '
0&
bx %
bx $
1#
bx "
bx !
$end
#1
b100 %
b100 -
b0 $
b0 ,
1&
#3
b1000 0
#5
b0 !
b0 /
b0 "
b0 .
0#
#9
0&
#10
1#
#14
1(
b1011111 '
b1011111 *
b10 )
b10 +
#15
0#
#20
1#
#24
0(
#25
b10 $
b10 ,
0#
#27
b1011111 "
b1011111 .
#30
1#
#34
b1 $
b1 ,
1(
b11100 '
b11100 *
b1 )
b1 +
#35
0#
#36
b0 "
b0 .
#40
1#
#44
b11100 "
b11100 .
0(
#45
0#
#50
1#
#54
1(
b110 '
b110 *
b100 )
b100 +
#55
0#
#60
1#
#64
b110 !
b110 /
b1111 '
b1111 *
#65
0#
#70
1#
#74
b1111 !
b1111 /
0(
#75
0#
#80
1#
1(
b110010 '
b110010 *
b1 )
b1 +
#84
b110010 "
b110010 .
#85
0#
0(
