Labs/Processor/Lab05/part03/submitted/adder.v
/*
Author - W M D U Thilakarathna
Reg No - E/16/366
*/

module adder(INPUT1, INPUT2, RESULT); // adder module

    input [31:0] INPUT1, INPUT2; // declare inputs
    output reg [31:0] RESULT;    // declare outputs

    always @(*) 
    begin
      #2 RESULT = INPUT1 + INPUT2; // add two numbers 
    end

endmodule

Labs/Processor/Lab05/part03/submitted/alu.v
/*
Author - W M D U Thilakarathna
Reg No - E/16/366
*/

module alu(DATA1, DATA2, RESULT, SELECT);
input [7:0] DATA1, DATA2; //declare the inputs
input [2:0] SELECT; //declare the select input
output [7:0] RESULT; //declare the output

reg [7:0] RESULT; // declare the outputs as registers

always @ (DATA1, DATA2, SELECT) // this block run if there is any change in DATA1 or DATA2 or SELECT
begin
    case (SELECT)
    3'b000:
        #1 RESULT = DATA2; //forward operation  1
    3'b001:
        #2 RESULT = DATA1 + DATA2; // add operation 2
    3'b010:
        #1 RESULT = DATA1 & DATA2; // bitwise and operation 1
    3'b011:
        #1 RESULT = DATA1 | DATA2; // bitwise or operation 1
    default: RESULT = 0; //result 0 if the other cases
    endcase
end
    
endmodule

Labs/Processor/Lab05/part03/submitted/mux2to1.v
/*
Author - W M D U Thilakarathna
Reg No - E/16/366
*/

module mux2to1(INPUT1, INPUT2, RESULT, SELECT);
    input [7:0] INPUT1, INPUT2; //declare inputs of the module
    input SELECT;               //declare inputs
    output reg [7:0] RESULT;    //declare outputs

    always @(*)
    begin
      if (SELECT == 1'b0)  //selecting according to the select signal
            RESULT = INPUT1;
      else 
            RESULT = INPUT2;
    end

endmodule

Labs/Processor/Lab05/part03/twosComp.v
module twosComp(INPUT, RESULT); //change this
    input [7:0] INPUT;       //declare inputs
    output reg [7:0] RESULT; //declare outputs

    always @ (INPUT)
    begin
      RESULT = ~INPUT + 1; // 2s comp negative
    end

endmodule

Labs/Processor/Lab05/part03/reg_file.v
module reg_file(IN, OUT1, OUT2, INADDRESS, OUT1ADDRESS, OUT2ADDRESS, WRITE, CLK, RESET);

input [7:0] IN;  // 8 bit data input
input [2:0] INADDRESS, OUT1ADDRESS, OUT2ADDRESS; // 3 bit data inputs
input WRITE, CLK, RESET; // 1 bit data inputs
output [7:0] OUT1, OUT2; // 8 bit data outputs

reg [7:0] registers [7:0]; // 8x8 register file

integer i;

assign #2 OUT1 = registers[OUT1ADDRESS]; //writing data to outputs
assign #2 OUT2 = registers[OUT2ADDRESS]; //writing data to outputs

always @ (posedge CLK) // this code block run when we are in a positive clock edge
begin
    // write input to the in address
    if (WRITE == 1'b1)
        #2 registers[INADDRESS] = IN;     
end


// combinational logic output for reset signal (level triggered input)
always @ (*)
begin
    if (RESET == 1'b1)
    begin
        #2 
        for (i = 0; i < 8; i++) //looping through register file and setting them to 0s
        begin
            registers[i] = 0;
        end   
    end
    
end

endmodule

Labs/Processor/Lab05/part03/control_unit.v
/*
Author - W M D U Thilakarathna
Reg No - E/16/366
*/

module control_unit(OP, twoscompMUXSEL, immeMUXSEL, regWRITEEN, aluOP);

    parameter [7:0] ADD   = 8'h00, 
                    SUB   = 8'h01,
                    AND   = 8'h02,
                    OR    = 8'h03,
                    MOV   = 8'h04,
                    LOADI = 8'h05;

    input [7:0] OP; //input op code
    output reg twoscompMUXSEL, immeMUXSEL, regWRITEEN; //output registers
    output reg [2:0] aluOP;

    always @ (*)
    begin
      case (OP)
        ADD:
            begin
                #1
                twoscompMUXSEL = 1'b0; //twos compliment select mux
                immeMUXSEL = 1'b0;     //immediate value select mux
                regWRITEEN = 1'b1;     //regwrite enable pin
                aluOP = 3'b001;        //cpu op code  
            end

        SUB:
            begin
                #1
                twoscompMUXSEL = 1'b1; //twos compliment select mux
                immeMUXSEL = 1'b0;     //immediate value select mux
                regWRITEEN = 1'b1;     //regwrite enable pin
                aluOP = 3'b001;        //cpu op code  
            end

        AND:
            begin
                #1
                twoscompMUXSEL = 1'b0; //twos compliment select mux
                immeMUXSEL = 1'b0;     //immediate value select mux
                regWRITEEN = 1'b1;     //regwrite enable pin
                aluOP = 3'b010;        //cpu op code  
            end

        OR:
            begin
                #1
                twoscompMUXSEL = 1'b0; //twos compliment select mux
                immeMUXSEL = 1'b0;     //immediate value select mux
                regWRITEEN = 1'b1;     //regwrite enable pin
                aluOP = 3'b011;        //cpu op code  
            end

        MOV:
            begin
                #1
                twoscompMUXSEL = 1'b0; //twos compliment select mux
                immeMUXSEL = 1'b0;     //immediate value select mux
                regWRITEEN = 1'b1;     //regwrite enable pin
                aluOP = 3'b000;        //cpu op code  
            end

        LOADI:
            begin
                #1
                twoscompMUXSEL = 1'b0; //twos compliment select mux
                immeMUXSEL = 1'b1;     //immediate value select mux
                regWRITEEN = 1'b1;     //regwrite enable pin
                aluOP = 3'b000;        //cpu op code  
            end
        endcase
    end

endmodule

Labs/Processor/Lab05/part03/cpu.v
/*
Author - W M D U Thilakarathna
Reg No - E/16/366
*/

`include "alu.v"
`include "reg_file.v"
`include "control_unit.v"
`include "twosComp.v"
`include "mux2to1.v"
`include "adder.v"

module cpu(PC, INSTRUCTION, CLK, RESET);

    input [31:0] INSTRUCTION; //fetched INSTRUCTIONtructions
    input CLK, RESET; // clock and reset for the cpu
    output reg [31:0] PC; //programme counter

    wire [7:0] SOURCE1, SOURCE2, DESTINATION, OP;  //decoded INSTRUCTIONtructons
    wire twoscompMUXSEL, immeMUXSEL, regWRITEEN;   //control signals
    wire [2:0] aluOP; // alu op code

    wire [7:0] REGOUT1, REGOUT2; //register file outputs
    wire [7:0] ALOP1, ALOP2, ALUOUT; //alu signal
    wire [7:0] TWOSCOMPOUT; //output of the twos complement
    wire [7:0] TWOSMUXOUT; //output of the twos compliment mux

    wire [31:0] PCNEXT; //store the next value of the pc

    //initiating the modules
    control_unit mycu (OP, twoscompMUXSEL, immeMUXSEL, regWRITEEN, aluOP); //control unit module
    reg_file myreg (ALUOUT, REGOUT1, REGOUT2, DESTINATION[2:0], SOURCE1[2:0], SOURCE2[2:0], regWRITEEN, CLK, RESET); //alu module
    twosComp twos (REGOUT2, TWOSCOMPOUT); // twos complement unit
    mux2to1 muxtwos (REGOUT2, TWOSCOMPOUT, TWOSMUXOUT, twoscompMUXSEL); //mux for two to one in the 2s complement selection
    mux2to1 muximme (TWOSMUXOUT, SOURCE2, ALOP1, immeMUXSEL); //immmediate value load mux
    alu myalu (ALOP2, ALOP1, ALUOUT, aluOP); //alu module 
    adder myadder (PC, 32'h00000004, PCNEXT); //adder to increment the cpu

    // decoding the INSTRUCTIONtructions
    assign DESTINATION = INSTRUCTION[23:16];
    assign SOURCE1 = INSTRUCTION[16:8];
    assign SOURCE2 = INSTRUCTION[7:0];
    assign OP = INSTRUCTION[31:24];

    assign ALOP2 = REGOUT1; //connect regout1 with the alu oparand 2

    always @ (posedge CLK)
    begin
      if (RESET == 1'b1) PC = -4; // rest the pc counter
      else #1 PC = PCNEXT;        // increment the pc
    end

    always @ (*)
    begin
      if (RESET == 1'b1) PC = -4; //asynchronus reset for the cpu
    end

endmodule

Labs/Processor/Lab05/part03/submitted/testbenchCPU.v
/*
Author - W M D U Thilakarathna
Reg No - E/16/366
*/

`include "cpu.v"

module testbenchCPU;
    
    //input registers
    wire [31:0] INS;
    reg CLK, RESET; 
    reg [7:0] INST_MEMORY [1023:0] ; //instruction array

    wire[31:0] PC;
    
    cpu mycpu(PC, INS, CLK, RESET); //initialize the cpu

    initial // instruction array
    begin
      //monitor command to check the content od the register file
      $monitor($time, " REG0: %b  REG1: %b  REG2: %b  REG3: %b  REG4: %b  REG5: %b  REG6: %b  REG7: %b ",
                          mycpu.myreg.REGISTERS[0], mycpu.myreg.REGISTERS[1], mycpu.myreg.REGISTERS[2], 
                          mycpu.myreg.REGISTERS[3], mycpu.myreg.REGISTERS[4], mycpu.myreg.REGISTERS[5], 
                          mycpu.myreg.REGISTERS[6], mycpu.myreg.REGISTERS[7]);
      // generate files needed to plot the waveform using GTKWave
      $dumpfile("cpu_wavedata.vcd");
      $dumpvars(0, testbenchCPU);
    end

    assign #2 INS = {INST_MEMORY[PC + 3], INST_MEMORY[PC + 2], INST_MEMORY[PC + 1], INST_MEMORY[PC]}; //fetching instruction
       
    initial
    begin
         // loadi 0 0x0A
        {INST_MEMORY[3],INST_MEMORY[2],INST_MEMORY[1],INST_MEMORY[0]}     = 32'b00000101_00000000_00000000_00001010;
        // mov 1 0
        {INST_MEMORY[7],INST_MEMORY[6],INST_MEMORY[5],INST_MEMORY[4]}     = 32'b00000100_00000001_00000000_00000000;
        // loadi 2 0x05
        {INST_MEMORY[11],INST_MEMORY[10],INST_MEMORY[9],INST_MEMORY[8]}   = 32'b00000101_00000010_00000000_00000101;
        // add 3 1 2
        {INST_MEMORY[15],INST_MEMORY[14],INST_MEMORY[13],INST_MEMORY[12]} = 32'b00000000_00000011_00000001_00000010;
        // sub 3 1 2
        {INST_MEMORY[19],INST_MEMORY[18],INST_MEMORY[17],INST_MEMORY[16]} = 32'b00000001_00000011_00000001_00000010;
        // or 3 1 2
        {INST_MEMORY[23],INST_MEMORY[22],INST_MEMORY[21],INST_MEMORY[20]} = 32'b00000011_00000011_00000001_00000010;
        // and 3 1 2
        {INST_MEMORY[27],INST_MEMORY[26],INST_MEMORY[25],INST_MEMORY[24]} = 32'b00000010_00000011_00000001_00000010;

        CLK = 1'b1;
        
        // assign values with time to input signals to see output 
        RESET = 1'b1;

        #1
        RESET = 1'b0;

        #37
        RESET = 1'b1;
        #1
        RESET = 1'b0;

        #140
        $finish;
    end
    
    // clock signal generation
    always
    begin
      #7 CLK = ~CLK;       
    end              

endmodule

Labs/Processor/Lab05/part03/submitted/cpu_wavedata.vcd
$date
	Sun May 10 18:39:59 2020
$end
$version
	Icarus Verilog
$end
$timescale
	1s
$end
$scope module testbenchCPU $end
$var wire 32 ! PC [31:0] $end
$var wire 32 " INS [31:0] $end
$var reg 1 # CLK $end
$var reg 1 $ RESET $end
$scope module mycpu $end
$var wire 8 % ALOP2 [7:0] $end
$var wire 1 # CLK $end
$var wire 32 & INSTRUCTION [31:0] $end
$var wire 1 $ RESET $end
$var wire 1 ' twoscompMUXSEL $end
$var wire 1 ( regWRITEEN $end
$var wire 1 ) immeMUXSEL $end
$var wire 3 * aluOP [2:0] $end
$var wire 8 + TWOSMUXOUT [7:0] $end
$var wire 8 , TWOSCOMPOUT [7:0] $end
$var wire 8 - SOURCE2 [7:0] $end
$var wire 8 . SOURCE1 [7:0] $end
$var wire 8 / REGOUT2 [7:0] $end
$var wire 8 0 REGOUT1 [7:0] $end
$var wire 32 1 PCNEXT [31:0] $end
$var wire 8 2 OP [7:0] $end
$var wire 8 3 DESTINATION [7:0] $end
$var wire 8 4 ALUOUT [7:0] $end
$var wire 8 5 ALOP1 [7:0] $end
$var reg 32 6 PC [31:0] $end
$scope module muximme $end
$var wire 8 7 INPUT2 [7:0] $end
$var wire 1 ) SELECT $end
$var wire 8 8 INPUT1 [7:0] $end
$var reg 8 9 RESULT [7:0] $end
$upscope $end
$scope module muxtwos $end
$var wire 1 ' SELECT $end
$var wire 8 : INPUT2 [7:0] $end
$var wire 8 ; INPUT1 [7:0] $end
$var reg 8 < RESULT [7:0] $end
$upscope $end
$scope module myadder $end
$var wire 32 = INPUT1 [31:0] $end
$var wire 32 > INPUT2 [31:0] $end
$var reg 32 ? RESULT [31:0] $end
$upscope $end
$scope module myalu $end
$var wire 8 @ DATA1 [7:0] $end
$var wire 8 A DATA2 [7:0] $end
$var wire 3 B SELECT [2:0] $end
$var reg 8 C RESULT [7:0] $end
$upscope $end
$scope module mycu $end
$var wire 8 D OP [7:0] $end
$var reg 3 E aluOP [2:0] $end
$var reg 1 ) immeMUXSEL $end
$var reg 1 ( regWRITEEN $end
$var reg 1 ' twoscompMUXSEL $end
$upscope $end
$scope module myreg $end
$var wire 1 # CLK $end
$var wire 8 F IN [7:0] $end
$var wire 3 G INADDRESS [2:0] $end
$var wire 8 H OUT1 [7:0] $end
$var wire 3 I OUT1ADDRESS [2:0] $end
$var wire 8 J OUT2 [7:0] $end
$var wire 3 K OUT2ADDRESS [2:0] $end
$var wire 1 $ RESET $end
$var wire 1 ( WRITE $end
$var integer 32 L i [31:0] $end
$upscope $end
$scope module twos $end
$var wire 8 M INPUT [7:0] $end
$var reg 8 N RESULT [7:0] $end
$upscope $end
$upscope $end
$upscope $end
$enddefinitions $end
#0
$dumpvars
bx N
bx M
bx L
bx K
bx J
bx I
bx H
bx G
bx F
bx E
bx D
bx C
bx B
bx A
bx @
bx ?
b100 >
b11111111111111111111111111111100 =
bx <
bx ;
bx :
bx 9
bx 8
bx 7
b11111111111111111111111111111100 6
bx 5
bx 4
bx 3
bx 2
bx 1
bx 0
bx /
bx .
bx -
bx ,
bx +
bx *
x)
x(
x'
bx &
bx %
1$
1#
bx "
b11111111111111111111111111111100 !
$end
#1
0$
#2
b1000 L
b0 1
b0 ?
#7
0#
#14
1#
#15
b0 !
b0 6
b0 =
#17
b0 I
b0 4
b0 C
b0 F
b0 G
b0 .
b1010 5
b1010 9
b1010 A
b10 K
b0 3
b1010 -
b1010 7
b101 2
b101 D
b100 1
b100 ?
b101000000000000000000001010 "
b101000000000000000000001010 &
#18
b0 *
b0 B
b0 E
1(
1)
0'
#19
b0 +
b0 8
b0 <
b0 ,
b0 :
b0 N
b1010 4
b1010 C
b1010 F
b0 %
b0 @
b0 0
b0 H
b0 /
b0 ;
b0 J
b0 M
#21
0#
#28
1#
#29
b100 !
b100 6
b100 =
#31
b1 G
b0 5
b0 9
b0 A
b0 K
b1 3
b0 -
b0 7
b100 2
b100 D
b1000 1
b1000 ?
b100000000010000000000000000 "
b100000000010000000000000000 &
#32
b0 4
b0 C
b0 F
0)
b1010 %
b1010 @
b1010 0
b1010 H
#33
b1010 5
b1010 9
b1010 A
b1010 +
b1010 8
b1010 <
b11110110 ,
b11110110 :
b11110110 N
b1010 /
b1010 ;
b1010 J
b1010 M
#34
b1010 4
b1010 C
b1010 F
#35
0#
#38
b11111111111111111111111111111100 !
b11111111111111111111111111111100 6
b11111111111111111111111111111100 =
1$
#39
0$
#40
bx I
bx G
bx .
bx K
bx 3
bx -
bx 7
bx 2
bx D
b0 1
b0 ?
b1000 L
bx "
bx &
#42
bx 5
bx 9
bx A
bx +
bx 8
bx <
bx ,
bx :
bx N
bx %
bx @
bx 0
bx H
bx /
bx ;
bx J
bx M
1#
#43
bx 4
bx C
bx F
b0 !
b0 6
b0 =
#45
b0 I
b0 G
b0 .
b10 K
b0 3
b1010 -
b1010 7
b101 2
b101 D
b100 1
b100 ?
b101000000000000000000001010 "
b101000000000000000000001010 &
#46
b1010 5
b1010 9
b1010 A
1)
#47
b0 +
b0 8
b0 <
b0 ,
b0 :
b0 N
b1010 4
b1010 C
b1010 F
b0 %
b0 @
b0 0
b0 H
b0 /
b0 ;
b0 J
b0 M
#49
0#
#56
1#
#57
b100 !
b100 6
b100 =
#59
b1 G
b0 5
b0 9
b0 A
b0 K
b1 3
b0 -
b0 7
b100 2
b100 D
b1000 1
b1000 ?
b100000000010000000000000000 "
b100000000010000000000000000 &
#60
b0 4
b0 C
b0 F
0)
b1010 %
b1010 @
b1010 0
b1010 H
#61
b1010 5
b1010 9
b1010 A
b1010 +
b1010 8
b1010 <
b11110110 ,
b11110110 :
b11110110 N
b1010 /
b1010 ;
b1010 J
b1010 M
#62
b1010 4
b1010 C
b1010 F
#63
0#
#70
1#
#71
b1000 !
b1000 6
b1000 =
#73
b10 G
b101 K
b10 3
b101 -
b101 7
b101 2
b101 D
b1100 1
b1100 ?
b101000000100000000000000101 "
b101000000100000000000000101 &
#74
b101 5
b101 9
b101 A
1)
#75
b0 +
b0 8
b0 <
b0 ,
b0 :
b0 N
b101 4
b101 C
b101 F
b0 /
b0 ;
b0 J
b0 M
#77
0#
#84
1#
#85
b1100 !
b1100 6
b1100 =
#87
b1 I
b11 G
b1 .
b10 5
b10 9
b10 A
b10 K
b11 3
b10 -
b10 7
b0 2
b0 D
b10000 1
b10000 ?
b110000000100000010 "
b110000000100000010 &
#88
b0 5
b0 9
b0 A
b10 4
b10 C
b10 F
b1 *
b1 B
b1 E
0)
#89
b101 5
b101 9
b101 A
b101 +
b101 8
b101 <
b11111011 ,
b11111011 :
b11111011 N
b101 /
b101 ;
b101 J
b101 M
#90
b1111 4
b1111 C
b1111 F
#91
0#
#98
1#
#99
b10000 !
b10000 6
b10000 =
#101
b1 2
b1 D
b10100 1
b10100 ?
b1000000110000000100000010 "
b1000000110000000100000010 &
#102
b11111011 5
b11111011 9
b11111011 A
b11111011 +
b11111011 8
b11111011 <
1'
#104
b101 4
b101 C
b101 F
#105
0#
#112
1#
#113
b10100 !
b10100 6
b10100 =
#115
b11 2
b11 D
b11000 1
b11000 ?
b11000000110000000100000010 "
b11000000110000000100000010 &
#116
b101 5
b101 9
b101 A
b101 +
b101 8
b101 <
b11 *
b11 B
b11 E
0'
#117
b1111 4
b1111 C
b1111 F
#119
0#
#126
1#
#127
b11000 !
b11000 6
b11000 =
#129
b10 2
b10 D
b11100 1
b11100 ?
b10000000110000000100000010 "
b10000000110000000100000010 &
#130
b10 *
b10 B
b10 E
#131
b0 4
b0 C
b0 F
#133
0#
#140
1#
#141
b11100 !
b11100 6
b11100 =
#143
bx I
bx G
bx .
bx K
bx 3
bx -
bx 7
bx 2
bx D
b100000 1
b100000 ?
bx "
bx &
#145
bx 5
bx 9
bx A
bx +
bx 8
bx <
bx ,
bx :
bx N
bx %
bx @
bx 0
bx H
bx /
bx ;
bx J
bx M
#146
bx 4
bx C
bx F
#147
0#
#154
1#
#155
b100000 !
b100000 6
b100000 =
#157
b100100 1
b100100 ?
#161
0#
#168
1#
#169
b100100 !
b100100 6
b100100 =
#171
b101000 1
b101000 ?
