Labs/Processor/Lab05/part01/alu.v
module alu(DATA1, DATA2, RESULT, SELECT);
input [7:0] DATA1, DATA2; //declare the inputs
input [2:0] SELECT; //declare the select input
output [7:0] RESULT; //declare the output

reg [7:0] RESULT; // declare the outputs as registers

always @ (DATA1 or DATA2 or SELECT) // this block run if there is any change in DATA1 or DATA2 or SELECT
begin
    case (SELECT)
    'b000:
        RESULT = #1 DATA2; //forward operation  
    'b001:
        RESULT = #2 DATA1 + DATA2; // add operation
    'b010:
        RESULT = #1 DATA1 & DATA2; // bitwise and operation
    'b011:
        RESULT = #1 DATA1 | DATA2; // bitwise or operation
    default: RESULT = 0; //result 0 if the other cases
    endcase
end
    
endmodule

Labs/Processor/Lab05/part01/testbench.v
`include "alu.v"

module testBench;

reg [7:0] DATA1, DATA2; // inputs to the alu
reg [2:0] SELECT;      // select input for the alu
wire [7:0] RESULT;    // outputs from the mux

alu myALU(DATA1, DATA2, RESULT, SELECT); // initialize the alu object

initial
begin
    $dumpfile("testalu.vcd"); // dumping the variables
    $dumpvars(0, testBench);
end

initial
begin
    DATA1 = 28;
    DATA2 = 38;
    SELECT = 0;
    #5 // delay of 1ns

    DATA1 = 28;
    DATA2 = 38;
    SELECT = 1;
    #5 // delay of 1ns

    DATA1 = 28;
    DATA2 = 38;
    SELECT = 2;
    #5 // delay of 1ns

    DATA1 = 28;
    DATA2 = 38;
    SELECT = 3;
    #5 // delay of 1ns
    
    #1
    $finish;
end

endmodule

Labs/Processor/Lab05/part01/testalu.vcd
$date
	Fri May  1 13:16:59 2020
$end
$version
	Icarus Verilog
$end
$timescale
	1s
$end
$scope module testBench $end
$var wire 8 ! RESULT [7:0] $end
$var reg 8 " DATA1 [7:0] $end
$var reg 8 # DATA2 [7:0] $end
$var reg 3 $ SELECT [2:0] $end
$scope module myALU $end
$var wire 8 % DATA1 [7:0] $end
$var wire 8 & DATA2 [7:0] $end
$var wire 3 ' SELECT [2:0] $end
$var reg 8 ( RESULT [7:0] $end
$upscope $end
$upscope $end
$enddefinitions $end
#0
$dumpvars
bx (
b0 '
b100110 &
b11100 %
b0 $
b100110 #
b11100 "
bx !
$end
#1
b100110 !
b100110 (
#5
b1 $
b1 '
#7
b1000010 !
b1000010 (
#10
b10 $
b10 '
#11
b100 !
b100 (
#15
b11 $
b11 '
#16
b111110 !
b111110 (
