Labs/Processor/Lab05/part03/email/alu.v
module alu(DATA1, DATA2, RESULT, SELECT);
input [7:0] DATA1, DATA2; //declare the inputs
input [2:0] SELECT; //declare the select input
output [7:0] RESULT; //declare the output

reg [7:0] RESULT; // declare the outputs as registers

always @ (*) // this block run if there is any change in DATA1 or DATA2 or SELECT
begin
    case (SELECT)
    'b000:
        RESULT = #1 DATA2; //forward operation  1
    'b001:
        RESULT = #2 DATA1 + DATA2; // add operation 2
    'b010:
        RESULT = #1 DATA1 & DATA2; // bitwise and operation 1
    'b011:
        RESULT = #1 DATA1 | DATA2; // bitwise or operation 1
    default: RESULT = 0; //result 0 if the other cases
    endcase
end
    
endmodule

Labs/Processor/Lab05/part03/email/mux2to1.v
module mux2to1(INPUT1, INPUT2, RESULT, SELECT);
    input [7:0] INPUT1, INPUT2; //declare inputs of the module
    input SELECT;               //declare inputs
    output reg [7:0] RESULT;    //declare outputs

    always @(*)
    begin
      if (SELECT == 1'b0)  //selecting according to the select signal
            RESULT = INPUT1;
      else 
            RESULT = INPUT2;
    end

endmodule

Labs/Processor/Lab05/part03/email/twosComp.v
module twosComp(INPUT, RESULT); //change this
    input [7:0] INPUT;       //declare inputs
    output reg [7:0] RESULT; //declare outputs

    always @ (INPUT)
    begin
      RESULT = INPUT*-1; // 2s comp negative
    end

endmodule

Labs/Processor/Lab05/part03/reg_file.v
module reg_file(IN, OUT1, OUT2, INADDRESS, OUT1ADDRESS, OUT2ADDRESS, WRITE, CLK, RESET);

input [7:0] IN;  // 8 bit data input
input [2:0] INADDRESS, OUT1ADDRESS, OUT2ADDRESS; // 3 bit data inputs
input WRITE, CLK, RESET; // 1 bit data inputs
output [7:0] OUT1, OUT2; // 8 bit data outputs

reg [7:0] registers [7:0]; // 8x8 register file

integer i;

assign #2 OUT1 = registers[OUT1ADDRESS]; //writing data to outputs
assign #2 OUT2 = registers[OUT2ADDRESS]; //writing data to outputs

always @ (posedge CLK) // this code block run when we are in a positive clock edge
begin
    // write input to the in address
    if (WRITE == 1'b1)
        #2 registers[INADDRESS] = IN;     
end


// combinational logic output for reset signal (level triggered input)
always @ (*)
begin
    if (RESET == 1'b1)
    begin
        #2 
        for (i = 0; i < 8; i++) //looping through register file and setting them to 0s
        begin
            registers[i] = 0;
        end   
    end
    
end

endmodule

Labs/Processor/Lab05/part03/email/control_unit.v
module control_unit(OP, twoscompMUXSEL, immeMUXSEL, regWRITEEN, aluOP);
    input [7:0] OP; //input op code
    output reg twoscompMUXSEL, immeMUXSEL, regWRITEEN; //output registers
    output reg [2:0] aluOP;

    always @ (*)
    begin
      case (OP)
        'h00: 
            begin
                twoscompMUXSEL = 1'b0; //twos compliment select mux
                immeMUXSEL = 1'b0;     //immediate value select mux
                regWRITEEN = 1'b1;     //regwrite enable pin
                aluOP = 3'b001;        //cpu op code  
            end

        'h01: 
            begin
                twoscompMUXSEL = 1'b1; //twos compliment select mux
                immeMUXSEL = 1'b0;     //immediate value select mux
                regWRITEEN = 1'b1;     //regwrite enable pin
                aluOP = 3'b001;        //cpu op code  
            end

        'h02: 
            begin
                twoscompMUXSEL = 1'b0; //twos compliment select mux
                immeMUXSEL = 1'b0;     //immediate value select mux
                regWRITEEN = 1'b1;     //regwrite enable pin
                aluOP = 3'b010;        //cpu op code  
            end

        'h03: 
            begin
                twoscompMUXSEL = 1'b0; //twos compliment select mux
                immeMUXSEL = 1'b0;     //immediate value select mux
                regWRITEEN = 1'b1;     //regwrite enable pin
                aluOP = 3'b011;        //cpu op code  
            end

        'h04: 
            begin
                twoscompMUXSEL = 1'b0; //twos compliment select mux
                immeMUXSEL = 1'b0;     //immediate value select mux
                regWRITEEN = 1'b1;     //regwrite enable pin
                aluOP = 3'b000;        //cpu op code  
            end

        'h05: 
            begin
                twoscompMUXSEL = 1'b0; //twos compliment select mux
                immeMUXSEL = 1'b1;     //immediate value select mux
                regWRITEEN = 1'b1;     //regwrite enable pin
                aluOP = 3'b000;        //cpu op code  
            end
        endcase
    end

endmodule

Labs/Processor/Lab05/part03/email/cpu.v
`include "alu.v"
`include "reg_file.v"
`include "control_unit.v"
`include "twosComp.v"
`include "mux2to1.v"

module cpu(PC, INS, CLK, RESET);

    /*
    op codes
    00000000 - add
    00000001 - sub
    00000010 - and
    00000011 - or
    00000100 - mov
    00000101 - loadi
    */

    input [31:0] INS; //fetched instructions
    input CLK, RESET; // clock and reset for the cpu
    output reg [7:0] PC; //programme counter

    reg [7:0] SOURCE1, SOURCE2, DESTINATION, OP; //decoded instructons
    wire twoscompMUXSEL, immeMUXSEL, regWRITEEN;       //control signals
    wire [2:0] aluOP;

    wire [7:0] REGOUT1, REGOUT2; //register file outputs
    wire [7:0] ALOP1, ALOP2, ALUOUT; //alu out signal
    wire [7:0] TWOSCOMPOUT; //output of the twos complement
    wire [7:0] TWOSMUXOUT; //output of the twos compliment mux

    //initiating the modules
    control_unit mycu (OP, twoscompMUXSEL, immeMUXSEL, regWRITEEN, aluOP); //control unit module
    reg_file myreg (ALUOUT, REGOUT1, REGOUT2, DESTINATION[2:0], SOURCE1[2:0], SOURCE2[2:0], regWRITEEN, CLK, RESET); //alu module
    twosComp twos (REGOUT2, TWOSCOMPOUT); // twos complement unit
    mux2to1 muxtwos (REGOUT2, TWOSCOMPOUT, TWOSMUXOUT, twoscompMUXSEL); //mux for two to one in the 2s complement selection
    mux2to1 muximme (TWOSMUXOUT, SOURCE2, ALOP1, immeMUXSEL); //immmediate value load mux
    alu myalu (ALOP2, ALOP1, ALUOUT, aluOP); //alu module 

    always @ (INS) // instruction decoding unit
    begin   
        #1     
        {OP, DESTINATION, SOURCE1, SOURCE2} = INS; //decode the instruction     
    end

    assign ALOP2 = REGOUT1; //connect regout1 with the alu oparand 2

    always @ (posedge CLK)
    begin
      if (RESET == 1'b1) PC = -4; // rest the pc counter
      else #1 PC = PC + 4;        // 
    end

endmodule

Labs/Processor/Lab05/part03/email/testbenchCPU.v
`include "cpu.v"

module testbenchCPU;
    
    //input registers
    wire [31:0] INS;
    reg CLK, RESET; 
    reg [31:0] instructions [255:0] ; //instruction array

    wire[7:0] PC;
    
    cpu mycpu(PC, INS, CLK, RESET); //initialize the cpu

    initial // instruction array
    begin
      instructions[0] = 32'h05000005;
      instructions[1] = 32'h05010007;
      instructions[2] = 32'h00030001; 
    end

    assign #2 INS = instructions[PC/4]; //fetching instruction
       
    initial
    begin
        CLK = 1'b1;
        
        // generate files needed to plot the waveform using GTKWave
        $dumpfile("cpu_wavedata.vcd");
		$dumpvars(0, testbenchCPU);
        
        // assign values with time to input signals to see output 
        RESET = 1'b1;

        #1
        RESET = 1'b0;

        /*
        #2
        INS = 32'h05000005;

        #17
        INS = 32'h05010107;

        #10
        INS = 32'h00000001;
        */

        #100
        $finish;
    end
    
    // clock signal generation
    always
    begin
      #7 CLK = ~CLK;       
    end              

endmodule

Labs/Processor/Lab05/part03/email/cpu_wavedata.vcd
$date
	Thu May  7 16:26:48 2020
$end
$version
	Icarus Verilog
$end
$timescale
	1s
$end
$scope module testbenchCPU $end
$var wire 32 ! INS [31:0] $end
$var wire 8 " PC [7:0] $end
$var reg 1 # CLK $end
$var reg 1 $ RESET $end
$scope module mycpu $end
$var wire 8 % ALOP2 [7:0] $end
$var wire 1 # CLK $end
$var wire 32 & INS [31:0] $end
$var wire 1 $ RESET $end
$var wire 1 ' twoscompMUXSEL $end
$var wire 1 ( regWRITEEN $end
$var wire 1 ) immeMUXSEL $end
$var wire 3 * aluOP [2:0] $end
$var wire 8 + TWOSMUXOUT [7:0] $end
$var wire 8 , TWOSCOMPOUT [7:0] $end
$var wire 8 - REGOUT2 [7:0] $end
$var wire 8 . REGOUT1 [7:0] $end
$var wire 8 / ALUOUT [7:0] $end
$var wire 8 0 ALOP1 [7:0] $end
$var reg 8 1 DESTINATION [7:0] $end
$var reg 8 2 OP [7:0] $end
$var reg 8 3 PC [7:0] $end
$var reg 8 4 SOURCE1 [7:0] $end
$var reg 8 5 SOURCE2 [7:0] $end
$scope module muximme $end
$var wire 8 6 INPUT2 [7:0] $end
$var wire 1 ) SELECT $end
$var wire 8 7 INPUT1 [7:0] $end
$var reg 8 8 RESULT [7:0] $end
$upscope $end
$scope module muxtwos $end
$var wire 1 ' SELECT $end
$var wire 8 9 INPUT2 [7:0] $end
$var wire 8 : INPUT1 [7:0] $end
$var reg 8 ; RESULT [7:0] $end
$upscope $end
$scope module myalu $end
$var wire 8 < DATA1 [7:0] $end
$var wire 8 = DATA2 [7:0] $end
$var wire 3 > SELECT [2:0] $end
$var reg 8 ? RESULT [7:0] $end
$upscope $end
$scope module mycu $end
$var wire 8 @ OP [7:0] $end
$var reg 3 A aluOP [2:0] $end
$var reg 1 ) immeMUXSEL $end
$var reg 1 ( regWRITEEN $end
$var reg 1 ' twoscompMUXSEL $end
$upscope $end
$scope module myreg $end
$var wire 1 # CLK $end
$var wire 8 B IN [7:0] $end
$var wire 3 C INADDRESS [2:0] $end
$var wire 8 D OUT1 [7:0] $end
$var wire 3 E OUT1ADDRESS [2:0] $end
$var wire 8 F OUT2 [7:0] $end
$var wire 3 G OUT2ADDRESS [2:0] $end
$var wire 1 $ RESET $end
$var wire 1 ( WRITE $end
$var integer 32 H i [31:0] $end
$upscope $end
$scope module twos $end
$var wire 8 I INPUT [7:0] $end
$var reg 8 J RESULT [7:0] $end
$upscope $end
$upscope $end
$upscope $end
$enddefinitions $end
#0
$dumpvars
bx J
bx I
bx H
bx G
bx F
bx E
bx D
bx C
bx B
bx A
bx @
bx ?
bx >
bx =
bx <
bx ;
bx :
bx 9
bx 8
bx 7
bx 6
bx 5
bx 4
b11111100 3
bx 2
bx 1
bx 0
bx /
bx .
bx -
bx ,
bx +
bx *
x)
x(
x'
bx &
bx %
1$
1#
b11111100 "
bx !
$end
#1
0$
#2
b1000 H
#7
0#
#14
1#
#15
b0 "
b0 3
#17
b101000000000000000000000101 !
b101000000000000000000000101 &
#18
b0 *
b0 >
b0 A
1(
1)
0'
b0 C
b0 E
b101 G
b101 0
b101 8
b101 =
b101 2
b101 @
b0 1
b0 4
b101 5
b101 6
#19
b101 /
b101 ?
b101 B
#20
b0 +
b0 7
b0 ;
b0 ,
b0 9
b0 J
b0 %
b0 <
b0 .
b0 D
b0 -
b0 :
b0 F
b0 I
#21
0#
#28
1#
#29
b100 "
b100 3
#31
b101000000010000000000000111 !
b101000000010000000000000111 &
#32
b1 C
b111 G
b111 0
b111 8
b111 =
b1 1
b111 5
b111 6
b101 %
b101 <
b101 .
b101 D
#35
0#
#42
1#
#43
b1000 "
b1000 3
#45
b110000000000000001 !
b110000000000000001 &
#46
b1 *
b1 >
b1 A
0)
b11 C
b1 G
b0 0
b0 8
b0 =
b0 2
b0 @
b11 1
b1 5
b1 6
#48
b101 0
b101 8
b101 =
b101 +
b101 7
b101 ;
b11111011 ,
b11111011 9
b11111011 J
b110 /
b110 ?
b110 B
b101 -
b101 :
b101 F
b101 I
#49
0#
#50
b1010 /
b1010 ?
b1010 B
#56
1#
#57
b1100 "
b1100 3
#59
bx !
bx &
#60
bx C
bx E
bx G
bx 2
bx @
bx 1
bx 4
bx 5
bx 6
#62
bx 0
bx 8
bx =
bx +
bx 7
bx ;
bx ,
bx 9
bx J
bx %
bx <
bx .
bx D
bx -
bx :
bx F
bx I
#63
0#
#64
bx /
bx ?
bx B
#70
1#
#71
b10000 "
b10000 3
#77
0#
#84
1#
#85
b10100 "
b10100 3
#91
0#
#98
1#
#99
b11000 "
b11000 3
